[
  {
    "title": "剰余金の配当に関するお知らせ（15:30）",
    "date": "20250416",
    "body": "各 位\n\n代表者名\n\nイミ\nで\n\n代 表\n\n2025 人\n\n社 名 株式会社コメダホールディングス\n取締役社長 甘利祐一\n\n(コード番号 : 3543、東証プライム・名証プレミア)\n\n問い合わせ先 取 締 役 CFO 清水宏樹\nTEL. 052-936-8880\n剰余金の配当に関するお知らせ\n当社は、2025年4 月16日付開催の取締役会において、下記のとおり、2025年 2 月28日を基準日とする剰\n余金の配当を行うことについて決議いたしましたので、お知らせいたします。\n記\n1.配当の内容\n決定額                  直近の配当予想                 前期実績\n(2025年 2月期)             (2024年4月12日公表)             (2024年2 月期)\n基準日                                      2025年 2 月28日                           同左                         2024年 2 月29晶\n1株当たり配当金         27円00銭            同左           27円00銭\n配当金の総額           1 228百万            ー           1, 237百万F\n効力発生日            2025年 5 月15日           ー           2024年 5 月15日\n配当原資                               利益刺余金                          ー                          利益剰余金\n2.配当の理\n当社は株主還元を経営上の重要な課題として認識しております。利益配分の方針としては、借入金の返\n済のほか、業績や事業拡大のための資金需要に対応した内部留保の確保を総合的に勘案した上で、中期経\n営計画「VALUES 2025」 のもとで中長期的に最適な資本配分を行うべく、 株主の皆さまに対するさらなる株\n主還元の柔軟性と安定性を強化するために、2026年 2 月期までの5ヵ年を対象とした中期経営計画期間累\n計の総還元性向を50%%以上とすることを目標としております。\n2025年 2 月期においては、中間配当として1 株当たり27円の配当を実施しました。 期末配当については\n1株当たり27円、年間配当金額1 株あたり54円の配当を実施いたします。また、2024年4 月10日の取締役\n会決議に基づく自己株式の取得(381, 900株) を実施 した結果、2025年2月期の総本元性向は59. 46%となりま\nした。 引き続き、中期経営計画期間累計で総還元性向を50%%以上とすることを目指してまいります。\n(ご参考) 年間配当の内訳\n\n1 株当たり配当金\n基準日                                           第2 四半期末                                  末                                     年間\n2022年 2 月期実績                        25円00銭                           26円00銭                           51円00銭\n2023年 2 月期実績                           26円00銭                              26円00銭                              52円00銭\n2024年 2 月期実績                           26円00銭                              27円00銭                              53円00銭\n2025年 2 月期実績                           27円00銭                              27円00銭                              54円00銭\n2026年 2 月期予想                         30円00銭                            30円00銭                            60円00銭"
  },
  {
    "title": "2025年2月期決算短信[IFRS](連結)（15:30）",
    "date": "20250409",
    "body": "Tommpoas\n3\n\n2025年2月期 決算短信[IFRS]\n\n(連結)\n\nNs\n\n2025年 4月9日\n\n/\n\n上場会社名        株式会社コメダホールディングス                                      上場取引所 東名\nコード番号       3543        URL http://www. komeda-holdings. co. jp/\n代表者              (役職名) 代表取締役社長                  (氏名) 甘利 祐一\n問合せ先責任者 (役職名) 常務取締役CFO              (氏名) 清水 宏樹       TEL 052-936-8880\n定時株主総会開催予定日    2025年 5 月29日            配当支払開始予定日 2025年5月15日\n有価証券報告書提出予定日 2025年5月28日\n決算補足説明資料作成の有無 : 有\n決算説明会開催の有無       :有 (機関投資家・アナリスト向け)\n(百万円未満四捨五入)\n1. 2025年 2 月期の連結業績 (2024年 3 月 1 日2025年 2 月28日)\n(1) 連結経営成績                                                                    (%表示は対前期増減率)\n素                  開                  本               、               親会社の所有者に      当期包括利益\n売上収益            営業利益           税引前利益           当期利益        帰属する当期利益         合計額\n百万円       %     百万円       %     百万円       %     百万円       %     百万円       %     百万円\n2025年2 月期    47.057    8.8    8.820    1.2    8.612| A0.8    5.814| A2.7    5.814| A2.6    5.897| A1.3\n2024年2 月期    43.236| 14.3    8.717    8.6    8.685    8.5    5.974    9.7    5.972| 10.1     5.975    9.6\n基本的 1株当たり             希薄化後          親会社所有者帰属持分         資産合計               売上収益\n当期利益            1株当たり当期利益          当期利益率            税引前利益率            営業利益率\n円 銭              円 銭               %               %               %\n2025年2 月期                    127.66                   127.62                   13.1                     8.3                   18.7\n2024年 2 月期                    130.12                   130.03                   14.3                    8.6                   20.2\n( 2) 連結財政状態\n資産合計        資本合計      親会社の所有者に    箱会社所有者    1株当たり親会社\na                      a四                帰属する持分            帰属持分比率         所有者帰属持分\n百万円              百万円              百万円               %            円 銭\n2025年2 月期                   105.739                   45.618                   45.618                   43.1              1.002.77\n2024年 2 月期                   102.772                   43.110                   43.110                   41.9                940.67\n( 3) 連結キャッシュ・フローの状況\n営業活動による             投資活動による            財務活動による           現金及び現金同等物\nキャッシュ・フロー        キャッシュ・フロー        キャッシュ・フロー            期末残高\n百万円                        百万円                        百万円                        百万円\n2025年2 月期                         11.235                           642                       9, 505                        10.390\n2024年2 月期                         11.437                       A1.955                       A8. 237                         7.923\n2. 配当の状況\n年間配当金                配当金総額| 品当性向 |親会社所有者\n昌  :   属持分配当\n第 1 四半期末 | 第2 四半期末 | 第3四半期末      期末          合計         合計)        (連結)     人人\n円 銭       円 銭       円 銭       円 銭      円 銭     百万円        %        %\n2024年 2 月其               ー       26.00         ー       27.00      53.00      2.429       40.7       5.8\n2025年 2 月其               ー       27.00         ー       27.00      54.00      2.456       42.3       5.5\n2026年 2 月期 (予想)                     ー              30.00                  ー              30.00            60.00                                 40.3\n3. 2026年2 月期の連結業績予想 (2025年3 月 1 日2026年 2 月28日)\n(%表示は、対前期増減率)\n未                 各                 ロar              a              親会社の所有者に| 基本的1株当たり\n売上収益         営業利益        税引前利益        当期利益     帰属する当期利益      当期利益\n百万円     %| 百万円     %| 百万円     %| 百万円     %| 百万円     %           円 銭\n通期             54.880| 16.6| 10.000| 13.4| 9.970| 15.8      6.850| 17.8      6.770| 16.4                148.82\n\n(注)\n\n「基本的 1株当たり当期利益」の算定上の基礎となる期中\n式数 (自己株式数を除く) を使\n\nしております。\n\nF均株式数については、2025年 2 月28日現在の発行済株\n) 和中に おける連結範囲の重要な変更 : 有\n新規 1社 (社名) KOMEDA INTERNATIONAL HOLDINGS PTE. LTD.\n\n) 会計方針の変更・会計上の見積りの変更\n\n① IFRSに より厩束される美和方針の恋昌 :  無\n\n② ①以外の会計方針の変更           : 無\n会計上の見積りの変更                  : 本\n\n) 発行済株式数 (普通株式)\n\n① 期末発行済株式数 (自己株式を含む)       2025年 2月期 ! 46.267.500株 | 2024年2月期! 46.235,400株\n② 期末自己株式数                                   2025年2月期         775, 905株 | 2024年2月期         410, 859株\n③ 期中平均株式数                                  2025年 2月期 ! 45.546.567株 | 2024年2月期! 45.892.171株\n\n※ 添付される連結財務諸表に対する公認会計士又は監査法人によるレビュー : 無\n\n※ 業績予想の適切な利用に関する説明、その他特記事項\n(将来に関する記述等についてのご注意)\n\n本資料に記載されている業績見通し等の将来に関する記述は、当社が現在入手している情報及び合理的であると\n判断する一定の前提に基づいており、当社としてその達成を約束する趣旨のものではありません。 実際の業績等は\n様々な要因により大きく異なる可能性があります。\n\n業績予想の前提となる仮定及び業績予想のご利用にあたっての注意事項については、添付資料3ページの「1.\n当期の経営成績等の概況 (4 ) 次期の見通し」をご参照ください。\n\n(決算補足説明資料の入手方法について)\n当社は、2025年 4 月11日 (金) 15:00より機関投資家及びアナリスト向けにライブ配信による説明会を開催する\n予定です。当日使用する決算説明資料は、開催後速やかに当社ウェブサイトに掲載する予定です。\n\n帆コメダホールディングス (3543) 2025年 2 月期\n\n〇添付資料の目次\n\n1. 経営成績等の概況\n\n(1 ) 当期の経営成績の概況\n(2 ) 当期の財政状態の概況\n(3 ) 当期のキャッシュ・フローの概況\n(4) 次期の見通し\n(5 ) 利益配分に関する基本方針及び当期・次期の配当\n. 会計基準の選択に関する基本的な考え方    …\n. 連結財務諸表及び主な注記\n) 連結財政状態計算書\n(2 ) 連結損益計算書 ……\n(3) 連結包括利益計算書\n(4) 連結持分変動計算書 … …\n(5) 連結キャッシュ・フロー計算書\n(6 ) 連結財務諸表に関する注記\n(継続企業の前提に関する注\n(セグメント情報)\n(売上収益)\n株あたり利益)\n(重要な後発事象)\n\n1. 経営成績等の概況\n\n(1 ) 当期の経営成績の\nF度における当社グループを取り巻く外食産業に\n外食震要は堅調に推移し、緩やかな\n\n当連結会計\n\nリスクによる原材料\nライフスタイル価\nこのような状況の\n社会をつなぐ』をス\nいりました。\n店舗においては、\nニュー価格の値上げ\n\n匠況\n\n帆コメダホールディングス (3543)\n\nSいては、賃上げやインバウンド需要\n\n還\n\n復傾向が継続しております。一方で、日米の金融政策や為替の\n\n格やエネルギーコス ト高騰の継続、人財\n直観の変化など、極めて先行きの不透明な\nもと、当社グループは、中期経営計画\nローガンに、既存モデルの拡充、新しv\n\n原材料価格やエネルギーコストの高騰に加え、人件費の上昇の影響を受\nを実施しました。 FC加盟店に対する負\n値上げを実施しました。一方で、店舗での値上げに対して、\n\n採用難による働き手不足や人件費の上\n業環境が続いております。\nVALUES 2025」に掲げる『“くつろぎ\"” で\nヽ共創価値の追求、財務価値の維持拡大に\n\nナて、4\nSりまし\n求めや\n\n箇格は8月末まで据え置いて\nデザートセットを今までよりも\n\n寺\n完\n\n2025年 2 月期\n\n算\n\n衣\n\n決\n\nの拡大により\n動向、地政学\n昇、お客様の\n\n人と地域と\nり組んでま\n\n月から店頭メ\nたが9月より\nすくするとと\n\nもに、一部の店舗においては改装を実施し、より一層くつろいでいただける空間づくりに取り組むなど、お客様の\n\n店舗体験価値向上を区\n\n売上高前\n\nるべくQ SC向上施策に努めてまいり\n\n販売施策としては、8月1日よりコメダ公式アプリで店信\nンク 1 杯無料券がプレゼントされるキャンベペーンを実施し、ア\nロノワール 天空の抹茶」、「シロノワール 本梗信玄餅」のよう【\n品や老舗和菓子店株式会社たねや様から生まれた洋菓子ブラン\nハリエ監修 ショコラノワール」を発売し、多くのお客様\n\nこれらの取り組みにより、当連結会計\nE比は110.59%となりました。\n\nました。\n#をお気に入り登録しスタンプを5個ため\nプリを通じてお客様利便性向\nこ地域に根ざしたブランドとのコラボ\nヾのクラブハリエとコラボレーション\nK店いただきました。\n\n)ー ご\nにご\n\nるごとにドリ\n\n上に努めたほか、「シ\n\nレーション商\nした「クラブ\n\nE度におけるFC加盟店向け卸売の既存店売上高前年上比は105.19%、全店\n\nまた、コメダ珈琲店について新規に57店舗を出店したほか、おかげ庵について 3店舗、新業態としてLa\nVinotheque、ジェリコ和堂、ベイス、米屋の太郎を出店 した結果、当連結会計年度示の店舗数は1, 083店舗となりま\nした。\n区分         エリア | 前連結会計年度末   新規出店      閉店     当連結会計年度末\n東日本      331 14)     20 (1)     1 (一)       350 (12)\n中京      304 (3)     6 (一)     1 (一)       309 (2)\nコメダ珈琲店\n西日本      330 (9 )     20 (一)      1 (一)       349 (8)\n海外       39 (13)     11 (5)     3 (1)        47 (19)\nおかげ庵             全国       13 (6)     3 (3)     ー (ー)        16 (8)\nBAKERY ADEMOK\nKOMEDA is\n大和館吉日\nLa Vinotheque         ー       6 (6)     6 (5)    ー (ー)       12 (11)\nジェリュ堂\nベイス\n米屋の太郎\n合計                       1.023 (51)     66 (14)     6 (1)      1, 083 (60)\n注1. ( ) 内の数字は直営店舗数であり、内数で記載しております。\n2. コメダ珈琲店の東日本エリアにおいて直営店 3 店舗、中京エリアにおいて直営店 1 店舗、西日本エリアにおいて直営店 1 店\n\n舗、おかげ庵において直営店 1 店舗をFC化しております。また、コメダ珈琲店の海外においてFC店2 店舗を直営化してお\n\nります。\n\n以上の取り組みの結果、当連結会\n\nた。一方で、コーヒ\n1.2%増) 、税引前和\n\n自カF\n\n[年度の売上収益は、47, 057百万円(前連結会計年度比8.8%増) となりまし\n豆など主要な原材料価格高騰の影響を受けて営業利益は8, 820百万円(前連結会計年度比\n人益は8, 612百万円(前連結会計年度比0.8%減) 、親会社の所有者に帰属する当期利益は5, 814\n\n(前連結会計年度比2. 6%減) となりました。\n\n短信\n\n言\nなお、当社グループは、\n\n題 (マテリアリティ) を「品質と\nに当社グループが経済価値の向上と社会課題の解決に真献すべく 、取り組みを実施しております。 詳細につきまし\nては、当社ホームページをご参照ください。\n\n・https://komeda-holdings. co. jp\n\n・https://komedacomestrue. kome,\n\n(2) 当期の財政状態の概況\n\nなりました。非流動資産は、有形固\n\n当連結会計4\n流動資産は、\n\n万\n\nとな\n\nた。\n\nまた、流動負償は、営業債務の増加等により前連結会計年度示に\nした。非流動負債は、借入金の減少等により前連結会計有\n\nFE度未における資産、\n現金及び現金同等】\n\nお客様」、\n\nりま\n\nした。その結果、資産は、\n\n前連結会計生\n\nた。その結果、負債は、前連結会計年度\n\n百\n\n資本は、\n\n万\n\n計上した\n\n取得したことによるものです。\n\n(3) 当期のキャッシュ・フローの概況\n\n当之結会\n連結全計年度に\n\n計年度における資金は、\n\n前連結会計和\n\n(営業活動によるキャッシュ・フロー)\n\n営業活動\n\n益8,612\n\n碧カPF\n\n結会計年度\n\nです。\n\nよる収入は11, 235百万\n(前連結会計年度比73百万\n\n「人と働きがい」、\n\n末に比べ459百万日\n前連結会計年度末に比べ2, 508百万F\n方で、親会社への所有者への剰余金の配当2, 465百万\n\n由コメダホールディングス\n\n/materiality/\nla. co. jp/action/\n\nE度未に比べ1,\n\n比べ906百万\nFE度未に比べ447百万\n増加し、60, 121百万\n\n(3543) 2025年2月期 決算短信\n\n『業活動を通じて持続可能な社会の実現に貢献するため、優先的に取り組むべき重要課\n「環境」の3つのテーマに分類し、この分類ごと\n\n負債及び資本の状況は次のとおりであります。\n物の増加等により前連結会計和\n定資産の増加等により前連結会計年度示に\nE度未に比べ2, 967百万F\n\n53百万\n比べ1, 8\n増加し、\n\n増加 し、20, 566百万円と\n4百万円増加し、85, 173百\n05, 739百万円となりまし\n\n増加\n減少し、45, 657百万F\nとなりました。\n\nとなりま\nなりまし\n\n14, 464百万F\nと\n\n増加し、45, 618百万\n\nとなりました。 これは主に当期利益を5, 814\n\nを実施\n\nしたこと、自己株式1 001百万円を\n\nF度未に比べ2, 467百万\nはける各キャッシュ・フローの状況とそれらの要因は次のとおりであります。\n\n増加し、10, 390百万\n\nとなりました。当\n\n(前連結会計年度比202百万\n\nE670百\n\n(投資活動によるキャッシュ・フロー)\n\n減少4, 000百万\n\n投資活動による収入は642百万\n(前連結会計年度は800百万F\n\n減) 、法人所得税等の支払額2, 731百万F\n\n減) を計上したこと、その他の金融負債の増加額3, 963百万F\n\n減)\n\nとなりました。これは主に、税引前利\n\n(前連\n\n(前連結会計\n\nの増加) 、連結の範|\n\n(前連結会計年度比124百万F\n\n減) によるもの\n\n年度は1, 955百万\n\nの支出) となりました。 これは主に定期預金の\n\nの変更を伴う子会社株式の取得による支出\n\n1, 889百万円 (前連結会計年度比1, 889百万円増) 、有形固定資産の取得による支出1, 187百万円 (前連結会計年度\n\n比152百万円増) によるものです。\n\n(財務活動によるキャッシュ・フロー)\n\n財務活動による支出は9, 505百万円 (前連結会計年度比1, 268百万円増) となかりました。これは主に借入金の返\n済による支出2, 032百万円 (前連結会計年度比91百万円増) 、リース負債の返済による支出4, 030百万円万 (前連\n結会計年度比268百万円増) 、自己株式の取得による支出1, 000百万円 (前連結会計年度比 0 百万円増) 、親会社\nの所有者への配当金の支払額2, 465百万円 (前連結会計年度比76百万円増) によるものです。\n(4) 次期の見通し\n\n当社グループを取り巻く外食業界においては、経済社会活動の正常\nクによる原材料価格やエネルギーコスト高\nフスタイル下価値観の変化など、依然として先行き不透明\nそのような経営環境の中、当社グレープは、中期経営計\n域と社会をつなぐ』をスローガンに、既存モデルの拡充、\nた各種施策を実施してまいります。\n\n上記を踏まえ、2026且\n\nE 2 月期の売上収益は54, 880百万円、\n、親会社の所有者に帰属する当期利益は6, 770百万\n\n購の継続、人財\n\nな状態カ\nト画「VALUES\n新しい共創\n\n採用難による\n想定されます。\n\nEが進展するものの、長期化する地政学リス\n働き手不足や人件費の上昇、お客様のライ\n\n2025」のもとで、『“くつろぎ\"” で人と地\n\n営業利益は10, 000百万\nを見込んでおります。\n\n『値の追求、財務価値の維持拡大を目的とし\n\n、税引前利益は9, 970百万\n帽コメダホールディングス (3543) 2025年2月期 決算短信\n\n(5 ) 利益配分に関する基本方針及び当期・次期の配当\n当社は株主還元を経営上の重要な課題と して認識しております。利益配分の方針としては、借入金の返済のほ\nか、業績や事業拡大のための資金需要に対応した内部留保の確保を総合的に勘案した上で、中期経営計画 「VALUES\n2025」 のもとで中長期的に最適な資本配分を行うべく、株主の皆さまに対するさらなる株主還元の柔軟性と安定性\nを強化するために、2026年 2 月期までの5ヵ年を対象とした中期経営計画期間泉計の総還元性向を509%以上とする\nことを目標としております。\n2025年 2 月期につきましては、中間配当として1株当たり27円の配当を実施 しました。期末配当については1株\n当たり27円、年間配当金額 1 株あたり54円の配当を実施する予定です。\n2026年 2 月期につきましては、営業利益を10, 000百万円とする目標を掲げるとともに、上記の中期経営計画にお\nける株主還元の目標を達成すべく、中間配当として1株当たり30円、期末配当として1株当たり30円、年間で1株\n当たり 6円の増配となる60円の配当を実施する予定です。\n\n. 会計基準の選択に関する基本的な考え方\n当社グループは、資本市場における財務情報の国際的な比較可能性及び利便性の向上を図るため、2014年3月1日を\n移行日として、2016年 2 月期より国際会計基準を適用しております。\n\n帆コメダホールディングス (3543) 2025年2月期 決算短信\n\n3. 連結財務諸表及び主な注記\n(1) 連結財政状態計算書\n\n(単位 : 碧万円)\n前連結会計年度                  当連結会計年度\n(2024年 2 月29日)                  (2025年 2 月28日)\n現金及び現金同等物                                                                        7, 923                               10, 390\n営業債権及びその他の債権                                                                6,054                                7, 208\nその他の金融資産                                                                   4, 133                                141\n棚卸資産                                                                                         373                                   433\nその他の流動資産                                                                      930                             2, 394\n流動資産合計                                                                               19, 413                               20, 566\n非流動資産\n有形固定資産                                                                       12, 880                            13, 838\nのれん                                                                                       38, 354                               38, 354\nその他の無形資産                                                                      357                               542\n営業債権及びその他の債権                                                              27, 636                               28, 213\nその他の金融資産                                                                    3, 417                             3, 498\n繰延税金資産                                                                                   265                                   199\nその他の非流動資産                                                                   450                               529\n非流動資産合計                                                                     83, 359                            85, 173\n資産合計                                                                                      102, 772                              105, 739\n負債及び資本\n負偵\n流動負債\n営業債務                                                                           2, 218                             2, 789\n借入金                                                                                            2, 032                                  2, 024\nリース負債                                           3, 895                 4, 050\n未払法人所得税                                                                                1, 621                                  1, 594\nその他の金融負債                                                              2, 618                            2, 776\nその他の流動負債                                                                  1,174                             1, 231\n流動負債合計                                                                             13, 558                               14, 464\n非流動負債\n借入金                                                                              9, 112                             7, 087\nリース負債                                                                                29, 438                               30, 822\nその他の金融負債                                                                 6, 709                             6, 790\n引当金                                                                                         359                                   396\nその他の非流動負債                                                                 486                               562\n非流動負債合計                                                                      46, 104                             45, 657\n負債合計                                                                     59, 662                         60, 121\n資本金                                                                                           659                                   672\n資本剰余金                                                                                  13, 042                                3, 062\n利益剰余金                                                                                       30, 476                                 33, 825\n自己株式                                                                           人1, 071                           人2, 028\nその他の資本の構成要素                                                                 4                                 87\n親会社の所有者に帰属する持分合計                                               43, 110                            45, 618\n非支配持分                                                                                        ー                                   人へ0\n資本合計                                             43, 110                45, 618\n\n負債及び資本合計                                                                           102, 772                              105, 739\n\n(2) 連結損益計算書\n\n中コメダホールディングス\n\n前連結会計年度\n(自2023年3月1 日\n至2024年 2 月29日)\n\n(3543) 2025年2月期 決\n\n(単位 : 百万円)\n当連結会計年度\n(自2024年3月1日\n至2025年 2 月28日)\n\n算\n\n昇\n\n売上収益\n\n売上原価\n\n売上総利益\n\nその他の営業収益\n販売費及び一般管理費\nその他の営業費)\n営業利益\n\n金融収益\n\n金融費/\n税引前利益\n法人所得税費/\n当期利益\n\n当期利益の帰属\n親会社の所有者\n非支配持分\n当期利益\n\n1 株当たり当期利益\n\n基本的1株当たり当期利益 (円)\n希薄化後 1 株当たり当期利益 (円)\n\n43, 236                            47, 057\n人へ28, 631                      人へ31, 377\n14, 605                            15, 680\n266                                   188\n\n人へ6, 012                           人へ7, 016\n人へ142                                  人へ32\n8, 717                             8, 820\n48                                    39\n\n人ムへ80                                人へ247\n\n8, 685                             8, 612\n\n人へ2, 711                           人2, 798\n5, 974                             5, 814\n5, 972                             5, 814\n\n2                                   へ0\n\n5, 974                             5, 814\n130.12                            127.66\n130.03                            127.62\n\n短信\n(3) 連結包括利益計算書\n\n中コメダホールディングス\n\n(3543)\n\n(単位 : 百万円)\n\n2025年2月期 決\n\n算\n\n昇\n\n当期利益\n\nその他の包括利益\n純損益に振り替えられる可能性のある項目\n在外営業活動体の換算差額\n税引後その他の包括利益\n当期包括利益\n\n当期包括利益の帰属\n親会社の所有者\n非支配持分\n当期包括利益\n\n前連結会計年度                  当連結会計年度\n(自2023年3月 1 日         (自2024年3月1日\n至2024年 2 月29日)        至2025年 2 月28日)\n5, 974                                5, 814\n1                                    83\n1                                    83\n5, 975                                5, 897\n5, 970                        5, 897\n5                                   ムA0\n5, 975                                5, 897\n\n短信\n帆コメダホールディングス\n\n(3543) 2025年2月期 決\n\n(単位 : 百万円)\n\n算\n\n昇和\n\n。      、 その他の 欠に人\n資本金       資本剰余金 利益剰余金 ^自己株式         資本の よる持分合 支配持分 資本合計\n構成要素          計\n2023年3月1日残高                  651        13.100        26.895         人へ109             6        40,543            76        40,619\n当期利益                                                                 5, 972                                              5, 972                 2           5, 974\nその他の包括利益                                                                               へ2            人へ2              3              1\n当期包括利益合計                          ー                ー           5, 972               ー              へ2           5, 970                 5           5, 975\n新株予約権の行使                     8              6                                                          14                            14\n株式報酬取引                                        53                                                          53                            53\n配当金                                                        人2, 391                                      ム2, 391                       人へ2, 391\n自己株式の取得                                   9                    へ1, 009                    へ1, 000                    人A1,000\n自己株式の処分                                人A47                         47                          ー                          ー\n非支配持分の取得                                 へ79                                                        へ79           人へ81          人へ160\n所有者との取引額合計            8       ムへ58     人2, 391      人へ962         ー     人へ3。403       人へ81     人へ3。 484\n2024年 2月29日残高            659     13, 042     30, 476     人へ1. 071         4     43,110        ー     43,110\n当期利益                                   5, 814                         5, 814       ムへ0      5, 814\nその他の包括利益                                                                                83             83              0             83\n当期包括利益合計                          ー                ー           5,814               ー               83           5, 897              ^0           5, 897\n新株予約権の行使                    13              9                                                          22                            22\n株式報酬取引                                        55                                                          55                            55\n配当金                                                               人へ2, 465                                          ムA2, 465                         人へ2, 465\n自己株式の取得                                   8                    へ1, 009                    へ1, 001                    人1, 001\n自己株式の処分                                ムA52                         52                          ー                          ー\n非支配株主との資本取引                                                                                ー             0             0\n所有者との取引額合計            13        20     人へ2, 465      人へ957         ー     人へ3。 389         0     人へ3。 389\n2025年 2月28日残高            672     13, 062     33,825     へ2. 028        87     45,618       ムへ0     45,618\n\n帆コメダホールディングス (3543) 2025年2月期 決算短信\n\n(5) 連結キャッシュ・フロー計算書\n\n(単位 : 和万円)\n前連結会計年度                 当連結会計年度\n(自2023年3月1日        (自2024年3月1日\n至2024年 2 月29日)               至2025年 2 月28日)\n営業活動によるキャッシュ・フロー\n税引前利益                                                                                8, 685                             8, 612\n減価償却費及び償却費                                                                 1, 583                            1, 572\n金融収益                                                                                 人へ48                             人へ39\n金融費                                                                                                80                                  247\n営業債権及びその他の債権の増減額 (へは増加)                    人1, 438               人1, 263\n差入保証金及び建設協力金の増減額 (へは増加)                                    人へ67                            人78\n営業債務の増減額 (へは減少)                                            136                      577\n預り保証金及び建設協力金の増減額 (へは減少)                                 170                          64\nその他の金融負債の増減額 (へは減少)                                                 4, 633                             3, 963\nその他                                                                                      91                            人136\n小計                                                 13, 825                13, 519\n利息の受取額                                                                                       22                                   35\n利息の支払額                                                                                    人へ42                                人58\n法人所得税等の支払額                                                              人へ2, 855                          人へ2, 731\n法人所得税等の本付額                                                                           487                                  470\n営業活動によるキャッシュ・フロー                             11, 437                11, 235\n投資活動によるキャッシュ・フロー\n定期預金の純増減 (へは増加)                                                         人へ800                            4, 000\n有形固定資産の取得による支出                               人へ1.035               人へ1, 187\n無形資産の取得による支出                                    人へ68                274\n投資有価証券の取得による支出                                 人へ38                 人25\n連結の範囲の変更を伴う子会社株式の取得による支出                    ー               人1, 889\nその他                                                                                    人へ14                                17\n投資活動によるキャッシュ・フロー                            人1. 955                  642\n財務活動によるキャッシュ・フロー\n世入による収入                                           1,000                   ー\n芽入金の返済による支出                                   人1, 941               人2, 032\nリース負債の返済による支出                                人へ3, 762               人4, 030\n株式の発行による収入                                                                     15                                22\n自己株式の取得による支出                                  人1,000               人へ1, 000\n親会社の所有者への配当金の支払額                                               人へ2, 389                         人2, 465\n連結の範囲の変更を伴わない子会社株式の取得による支                人160                  ー\n出\n財務活動によるキャッシュ・フロー                          人8, 237              人へ9, 505\n現金及び現金同等物に係る換算差額                                                       人3                                95\n現金及び現金同等物の増減額 (へは減少)                                               1, 242                            2, 467\n現金及び現金同等物の期首残高                                                                    6, 681                                 7, 923\n現金及び現金同等物の期末残高                                                                    7, 923                                10, 390\n\n|\nEi\nロ\n\nめ\n\n(6 ) 連結財務諾表に関する注記\n(継続企業の前提に関する注記)\n該当事項はありません。\n\n(セグメント情報)\n当社グループは、喫茶店のF C\n\n中コメダホールディングス\n\n#業の単二セグメントであるため、\n\n(3543)\n\n記載を省略しております。\n\n2025年 2 月期\n\n(売上収益)\n前連結会計年度          当連結会計年度\n(自 2023年3月1日      (自 2024年3月1日\n至 2024年 2 月29日)      至 2025年 2 月28日)\n卸売                                                                                     31, 084                          34, 727\n直営店売上                                                              5, 520                     5, 137\n店舗開発収入                                                                                1, 253                             1, 600\nその他                                                                                        3, 767                            3, 917\n顧客との契約から認識した収益 計                         41, 624              45, 381\nリースに係る収益                                      1, 612               1, 676\nその他の源泉から訟識した収益 計                                            1, 612                          1, 676\n合計                                                          43, 236                           47, 057\n(1 株あたり利益)\n前連結会計年度               当連結会計年度\n\n(自2023年3月1日       (自2024年3月1日\n\n至2024年 2 月29日)             至2025年 2 月28日)\n親会社の所有者に帰属する当期利益 (百万円)                           5, 972                   5, 814\n発行済普通株式の期中加重平均株式数 (株)                                45, 892, 171                   45, 546, 567\n希薄化効果のある普通株式数\n\nストック・オプション                                              33, 094                    15, 209\n\n希工化効果のある株式数を考慮した後の期中加重平均                                _\n株式数 (株)                                                                   45, 925, 265                   45, 561, 776\n基本的 1 株当たり当期利益 (円)                                               130.12                       127.66\n希薄化後 1 株当たり当期利益 (円)                                                130.03                         127.62\n\nー 10 一\n\n決算短信\n\n言\n帽コメダホールディングス (3543) 2025年2月期 決算短信\n\n(重要な後発事象)\n\n株式取得による企業結合\n当社は、2024年 9 月 6 日開催の取締役会決議に基づき、当社の完全子会社であるKOMEDA INTERNATIONAL HOLDINGS\n\nPTE. LTD. を通じてPOON RESOURCES PTE. LTD. (以下、「POON」という。) の発行済株式の70%を取得し、当社の連\n\n結子会社化の手続きを完了しました。\n\n1) 企業結合の概要\n① 被取得企業の名称及び事業の内容\n被取得企業の名称 :POON RESOURCES PTE. LTD\n事業の内容 : シンガボール国におけるカフェ及びタイ料理レストランの経営\n② 取得日    2025年3月 1 日\n③ 取得した議決権付資本持分の割合 70%\n④ 企業結合を行った主な理由\nシンガポール共和国内においてカフェ及びタイ料理チェーン店を複数店舗展開するPOONでは、ハラル対応のメ\nニューを提供する 3つのチェーン店を、病院内、公共施設、ショッピングモールなど地域に密着した場所へ店舗\n展開を行い、多くのお客様に “くつろぎ\"” を提供しております。\n当社は、当地において複数のプランドの店舗の展開能力を有するPOONの株式を取得 (当社の孫会社化) するこ\nとで、POONの事業に加えて、怒存のコメダ珈琲店のシンガポール国内及び東南アジア各国における展開について\n事業拡大の効果が期待でき、当社グループの企業価値拡大に資すると考えております。\n\n(2) 被取得企業の取得対価及びその内訳\n取得の対価 17百万シンガポールドル\n現金    17百万シンガポールドル\n\nー 11 一"
  },
  {
    "title": "2025年2月期第3四半期決算短信〔IFRS〕(連結)（15:30）",
    "date": "20250110",
    "body": "Tommpoas\n3\n\n2025年2月期 第3四半期決算短信[IFRS] (連結)\n2025年 1 月10日\n\n上場会社名       株式会社コメダホールディングス                                    上場取引所 東名\nコード番号       3543       URL http://www. komeda-holdings. co. jp/\n代表者             (役職名) 代表取締役社長                 (氏名) 甘利 祐一\n問合せ先責任者 (役職名) 常務取締役CFO              (氏名) 清水 宏樹       TEL 052-936-8880\n配当支払開始予定日           ー\n決算補足説明資料作成の有無 : 有\n決算説明会開催の有無       : 無\n(百万円未満四捨五入)\n1. 2025年2 月期第3四半期の連結業績 (2024年 3 月 1 日2024年11月30日)\n(1) 連結経営成績 (累計)                                                 (%表示は、対前年同四半期増減率)\n売上収益         営業利益        税引前利益       回天利半|所和有攻に少する   上半期台提益\n四半期利益          遇遇遇\n\n百万円      %| 百万円      %| 百万円      %| 百万円      %| 百万円      %| 百万円      %\n2025年2 月期第3四半期 | 34.665| 7.9| 6.698| 1.2    6.498| A1.5| 4.428| A1.5| 4428| A1.4| 4.545| 1.0\n2024年2 月期第3四半期 | 32.120| 16.6| 6.619| 13.9     6.599| 13.1     4.494| 13.1     4.492| 13.6| 4.501| 13.1\n\n基本的 1株当たり         希薄化後 1株当たり\n四半期利益                四半期利益\n円 銭                 円 銭\n\n2025年 2 月期第 3 四半期                97.19               97.15\n2024年 2 月期第 3 四半期                97.83               97.76\n\n(2 ) 連結財政状態\n\nの      ー           スロ\n和導計     生計    層する提人2 |\n百万円                   百万円                   百万円                        %\n2025年 2 月期第 3 四半其                     102,730                     44.248                     44.248                        43.1\n2024年 2 月                            102.772                 43.110                 43.110                   41.9\n2. 配当の状況\n年間配当金\n第 1四半期末     第2 四半期末     第3四半期末        期末            合計\n円 銭               円 銭               円 銭               円 銭               円 銭\n2024年 2 月                           ー              26.00                 ー              27.00              53.00\n2025年 2 月                           ー              27.00                 ー\n2025年 2 月期 予想)                                                                                            27.00                  54.00\n\n(注) 直近に公表されている配当予想からの修正の有無 : 無\n\n3. 2025年 2 月期の連結業績予想 (2024年 3 月 1 日一2025年 2 月28日)\n(%表示は、対前期増減率)\n\n末                   党                   重症                さ               親会社の所有者に | 基本的 1 株当たり\n売上収益          営業利益         税引前利益         当期利益      帰属する当期利益      当期利益\n百万円       %| 百万円       %| 百万円       %     百万円       %| 百万円       %              円 銭\n通期             45. 465     5.2     9.350     7.3     9, 285     6.9      6.330     6.0     6.330     6.0             138.14\n\n(注) 直近に公表されている業績予想からの修正の有無 : 無\n事項\n( 1 ) 当四半期連結果計期間における連結範囲の重要な変更 : 有\n新規 1社 (社名) KOMEDA INTERNATIONAL HOLDINGS PTE. LTD.\n\n( 2 ) 会計方針の変更・会計上の見積りの変更\n① IFRSにより要求される会計方針の変更 : 無\n② ①以外の会計方針の変更                     : 無\n会計上の見積りの変更         : 無\n\n(3) 発行済株式数 (普通株式)\n\n① 期末発行済株式数 (自己株式を含む) 2025年2月期3Q ! 46.260.900株| 2024年2月期  ! 46.235,400株\n② 期末自己株式数             2025年2月期3Q !   774, 455株 | 2024年2月期  !   410.859株\n③ 期中平均株式数 (四半期累計)     2025年2月期3Q ! 45.565.324株| 2024年2月期3Q ! 45.916,215株\n\n※ 添付される四半期連結財務諸表に対する公認会計士又は監査法人によるレビュー : 無\n\n※ 業績予想の適切な利用に関する説明、その他特記事項\n(将来に関する記述等についてのご注意)\n本資料に記載されている業績見通し等の将来に関する記述は、当社が現在入手している情報及び合理的であると\n判断する一定の前提に基づいており、当社としてその達成を約束する趣旨のものではありません。 実際の業績等は\n様々な要因により大きく異なる可能性があります。\n\n(決算補足説明資料の入手方法について)\n決算補足説明資料は、2025年 1 月10日に当社ウェブサイトに掲載する予定です。\n\n想コメダホールディングス (3543) 2025年2月期 第3四\n\n〇添付資料の目次\n\n1. 経営成績等の概況\n\n(1)\n(2)\n(3)\n\n当四半期の経営成績の概況\n当四半期の財政状態の概況\n連結業績予想などの将来予測情報に関する説明\n\n2. 要約四半期連結財務諸表及び主な注記\n\n(1)\n(2)\n(3)\n(4)\n(5)\n(6)\n\nM\n\n半期連結財政状態計算書\n四半期連結損益計算書\n半期連結包括利益計算書\n半期連結持分変動計算書\n四半期連結キャッシュ・フロー\n四半期連結財務諾表に関する注\n(継続企業の前提に関する注記)\n(会計方針の変更)\n(セグメント情報)\n(売上収益)\n( 1 株当た り 利益)   EE\n\nM\n\nM\n\n想コメダホールディングス (3543) 2025年2月期 第3四半期決算短信\n\n1. 経営成績の概況\n(1 ) 当四半期の経営成績の概況\n当第 3 四半期連結果計期間における当社グループを取り巻く外食産業は、賃上げやインバウンド需要の拡大によ\nり個人消費は堅調に推移し、緩やかな回復傾向が継続しております。 一方で、日米の金融政策や為替の動向、地政\n学リスクによる原材料価格やエネルギーコスト高騰の継続、人財採用難による働き手不足や人件費の上昇、お客様\nのライフスタイルや価値観の変化など、極めて先行き不透明な事業環境が続いております。\nこのような状況のもと、当社グループは、中期経営計画 「VALUES 2025」に掲げる『“くつろぎ” で、人と地域\nと社会をつなぐ』をスローガンに、既存モデルの拡充、新しい共創価値の追求、財務価値の維持拡大に取り組んで\nまいりました。\n店舗においては、原材料価格やエネルギーコストの高騰に加え、人件費の上昇の影響を受けて、 4月から店頭メ\nニュー価格の値上げを実施しました。 FC加盟店に対する卸売価格は8 月末まで据え置いておりましたが9月より\n値上げを実施しました。一方で、店舗での値上げに対して、デザートセットを今までよりもお求めやすい価格にす\nるとともに、一部の店舗においては改装を実施し、より一層くつろいでいただける空間づくりに取り組むなど、お\n客様の店舗体験価値向上を図るべくQ SC向上施策に努めてまいりました。また、販売施策としては、前年同期に\n実施したコメダグループ1, 000店舗を記念 した「1000キューキャンペーン」に対して、当期においてはコメダ珈琲\n店で使用できるお得な前売り回数券『コーヒーチケット』を、通常の9枚弘りと同じ価格で11枚弘りとして販売し\nたほか、前回発売時に人気を博した「コメ和牛」を復刻発売するとともに、株式会社グレープストーン様の東京土産\nの定番として幅広いお客様に愛される東京ばな奈とコラボレーションした 「東京ばな奈 シロノワール」 を発売\nK店いただきました。\nこれらの取り組みにより、当第3 四半期連結果計期間におけるFC加盟店向け卸売の既存店売上高前年比は\n103.59%、全店売上高前年上比は109.59%6となりました。\nコメダ珈琲店については国内を中心に新規に39店舗を出店し、おかげ庵について 1 店舗出店、La Vinothequeを\n\n店舗出店、新業態としてジェリュコ堂を1 店舗出店したほか、11月 1 日より事業を取得した「ハンバーガー如サン\nバドイッチ ベイス」を含めて、当第 3 四半期連結会計期間示の店舗数は1, 061店舗となりました。\nし            前連結会計      開             当第3 四半期\n区分      エリア   年度末     新規出店     閉店    連結会計其間未\n東日本     331 14)      13 (1)      ー (ご)      344 (13)\n中京      304 (3)      5 (一)      1 (一)     308 (2 )\n用\nコイク間拓計        西日本    330 (9 )     15 (一)     1 (一)    344 (8)\n海外       39 (13)      6 (2)      3 (1)      42 (16)\nおかげ庵          全国      13 (6)     1 (1)     ー (ご)    14 (6)\nBAKERY ADEMOK\nKOMEDA is\n大館吉日\nLa Vinothedme                         6 (6)        3 (2)            (一)         9 (8)\nジェリュっ和堂\nベイス\n合計 1.023 (51) 43 (6) 5 (1) 1.061 (53)\n(注) 1. ( ) 内の数字は直営店舗数であり、内数で記載しております。\n2. コメダ珈琲店の東日本エリアにおいて直営店 2店舗、中京エリアにおいて直営店 1 店舗、西日本エリ\nアにおいて直営店1 店舗、おかげ庵について直営店 1 店舗をFC化しております。また、コメダ珈琲\n\n店の海外においてFC店2店舗を直営化しております。\n\n以上の取り組みの結果、売上収益は34, 665百万円 (前年同期比7.9%増) となりました。 一方、コーヒー豆など\n主要な原材料価格高騰の影響を受けて営業利益は6,698百万円 (前年同期比1.2%増) 、税引前四半期利益は6, 498\n百万円 (前年同期比1.5%減) 、親会社の所有者に帰属する四半期利益は4, 428百万円 (前年同期比1.4%減) とな\nりました。\n\n想コメダホールディングス (3543) 2025年2月期 第3四半期決算短信\n\nなお、当社グループは、事業活動を通じて持続可能な社会の実現に頁献するため、優先的に取り組むべき重要課\n「品質とお客様」、 「人と働きがい」、「環境」の3つのテーマに分類し、この分類ごと\nに当社グループが経済価値の向上と社会課題の解決に真献すべく 、取り組みを実施しております。 詳細につきまし\nては、当社ホームページをご参照ください。\n\n題 (マテリアリティ) を\n\n・https://komeda-ho1dings. co. jp/materiality/\n\n・https://komedacomestrue. komeda. co. jp/action/\n\n(2 ) 当四半期の財政状態の概況\n\n①財政状態の分析\n\n当第 3 四半期連結会計期間末における資産、負債及び資本の状況は次のとおりです。\n流動資産は、その他の金融資産の減少等により前連結会計年度末に比べ679百万円減少し、18, 734百万円となり\nました。非流動資産は、営業債権及びその他の債権の増加等により前連結会計年度末に比べ637百万円増加し、\n\n83, 996百万円となりました。その結果、資産は、\n\nました。\n\nまた、流動負債は、未払法人所得税の減少等により前連結会計年度未に比べ597百万円減少し、12, 961百万円と\n\n前連結会計年度未に比べ42百万円減少し、102, 730百万\n\nとなり\n\nなりました。非流動負債は、借入金の減少等により前連結会計年度未に比べ583百万円減少し、45, 521百万円とな\n\nりました。その結果、負債は、前連結会計\n資本は、前連結会計年度未に比べ1, 138百万\n\nE度未と比べ1, 180百万円減少し、58, 482百万円となりました。\n増加し、44, 248百万円となりました。 これは主に、四半期利益を\n\n4, 428百万円計上した一方で、剰余金の配当2, 465百万円を実施したこと、自己株式1, 001百万円を取得したことに\n\nよるものです。\n\n②キャッシュ・フローの状況\n当第 3 四半期連結会計期間未における現金及び現金同等物は、前連結会計年度未に比べ1, 861百万円増加し、\n9, 784百万円となりました。\n\n当第 3 四半期連結果計期間における各キャッシュ・\n\n(営業活動によるキャッシュ・フロー)\n営業活動による収入は6, 631百万円 (前年同期比1, 060百万円減) となりました。これは主に税引前四半期利益\n6, 498百万円 (前年同期比101百万円減) を計上したこと、営業債権及びその他の債権の増加額1, 668百万円 (前\n\n(投資活動によるキャッシュ・フロー)\n\n投資活動による収入は3, 009百万円 (前年同期は733百万\n\n額4, 000百万円 (前年同\n減) によるものです。\n\nフローの状況とそれらの要因は次のとおりです。\n\n年同期比572百万円増) 、法人所得税等の支払額2, 742百万円 (前年同期比501百万円増) によるものです。\n\nの支出) となりました。 これは主に定期預金の減少\n\n期比3, 800百万円増) 、有形固定資産の取得による支出747百万円 (前年同期比139百万\n\n(財務活動によるキャッシュ・フロー)\n\n財務活動による支出は7, 887百万円 (前年同期比130百万\n支出1, 525百万円 (前年同期比65百\nH増) 、自己株式の取得による支出1, 000百万F\n\n額2, 411百万円 (前年同\n\n(3) 連結業績予想などの将#\n\n増) となりました。これは主に借入金の返済による\n\n万円増) 及びリース負債の返済による支出2, 968百万円 (前年同期比159百万\n\n期比73百万\n\n 予測情報に関する説明\n\n増) によるものです。\n\n(前年同期比0百万円増) 、親会社の所有者への配当金の支払\n\n2025年 2 月期の連結業績予想について、2024年 4 月10日に公表した通期連結業績予想からの変更はありません。\n\n政コメダホールディングス (3543) 2025年2月期 第3四半期決算短\n\n軸\n軸\n\n2 .     連結財務諾表及び主な注記\n(1 ) 要約四半期連結財政状態計算書\n(単位 : 百万円)\n前連結会計年度    当第 3 四半期連結会計期間\n(2024年 2 月29日)         (2024年11月30日)\n資産\n流動資産\n現金及び現金同等物                        7, 923           9, 784\n営業債権及びその他の債権                     6,054           7, 755\nその他の人金融資産                            4, 133            138\n棚卸資産                              373            448\nその他の流動資産                          930            609\n流動資産合計                                                                            19, 413                              18, 734\n非流動資産\n有形固定資産 12, 88012, 977\nのれん 38, 35438, 354\nその他の無形資産                          357            525\n営業債権及びその他の債権                      27, 636           27, 982\nその他の人金融資産                            3, 417           3, 499\n繰延税金資産                           265           142\nその他の非流動資産                         450            517\n非流動資産合計                                                  83, 359                    83, 996\n資産合計                                                         102, 772                   102, 730\n負債及び資本\n負債\n流動負債\n営業債務                            2, 218          2, 484\n借入金                                                   2, 032                     2, 025\nリース人負債                            3, 895           3, 913\n未払法人所得税                           1, 621             76\nその他の金融負債                         2, 618           2, 773\nその他の流動負債                       1, 174          1, 005\n流動負債合計                                                                         13, 558                              12, 96\n非流動負債\n借入金                                                                          9, 112                            7, 594\nリース人負債                                                    29, 438                    30, 218\nその他の金融負債                                                              6, 709                            6, 797\n引当金                                                                             359                              357\nその他の非流動負債                         486            555\n非流動負債合計                                                                46, 104                          45, 521\n負債合計                                                        59, 662                    58, 482\n資本\n資本金 659669\n資本剰余金                                                      13, 042                     3, 043\n利益剰余金                                                      30, 476                    32, 439\n自己株式                                                                        人1, 071                          2, 024\nその他の資本の構成要素                         4            121\n親会社の所有者に帰属する持分合計                                             43, 110                            44, 248\n資本合計                                                        43, 110                    44, 248\n負債及び資本合計                          102, 772         102, 730\n\nnl\n(2) 要約四半期連結損益計算書\n\n政コメダホールディングス (3543)\n\n2025年2月期 第3 四半期決算短1\n\n夢\n\n(単位 : 百万F\n\n前第 3 四半期連結果計期間\n(自 2023年3月1日\n至 2023年11月30日)\n\n当第 3 四半期連結果計期間\n(自 2024年3月1日\n至 2024年11月30日)\n\n売上収益\n\n売上原価\n\n売上総利益\n\nその他の営業収益\n販売費及び一般管理費\nその他の営業費)\n営業利益\n\n金融収益\n\n金融費/\n税引前四半期利益\n法人所得税費)\n四半期利益\n\n四半期利益の帰属\n親会社の所有者\n非支配持分\n四半期利益\n\n1株当たり四半期利益\n基本的1 株当たり四半期利益 (円)\n希藻化後 1 株当たり四半期利益 (円)\n\n(3) 要約四半期連結包括利益計算書\n\n32, 120                           34, 665\n人へ21, 181                        人へ22, 887\n10, 939                           11, 778\n142                                   92\n\n人へ4, 421                          人ムへ5, 161\n人へ41                                人へ11\n\n6, 619                            6, 698\n41                                   23\n\n人へ61                               人へ223\n\n6, 599                            6, 498\n\n人へ2, 105                         人へ2, 070\n4 494                            4 428\n4 492                            4 428\n\n2                                   ー\n\n4 494                            4 428\n97.83                            97.19\n97.76                            97.15\n\n(単位 : 碧万円)\n\n四半期利益\n\nその他の包括利益\n純損益に振り替えられる可能性のある項目\n在外営業活動体の換算差額\n税引後その他の包括利益\n半期包括利益\n\n半期包括利益の帰属\n親会社の所有者\n\n非支配持分\n\n四半期包括利益\n\n前第 3 四半期連結果計期間 当第3四半期連結時期間\n(自 2023年3月1日       (自 2024年3月1日\n\n至 2023年11月30日)       至 2024年11月30日)\n\n4, 494                              4, 428\n\n7                                 117\n\n7                                 117\n\n4, 501                              4. 545\n\n4, 496                              4. 545\n\n5                                   ー\n\n4, 501                              4. 545\n\n算\n\n昇和\n\n帆コメダホールディングス (3543) 2025年2月期 第3四半期決\n(4) 要約四半期連結持分変動計算書\n(単位 : 百万円)\n会社の\n区本金 次本人金利間欠 自選株式 mum に 人 人\nする持分合計\n\n2023年3月1日残高                    651        13, 100        26,895         人へ109             6        40,543            76        40,619\n四半期利益                                                                  4, 492                                               4, 492                 2           4. 494\nその他の包括利益                                                                                  4              4              3              7\n四半期包括利益合計                         ー               ー           4, 492               ー                4           4.496                5           4.501\n新株予約権の行使                       5              3                                                          8                             8\n株式報酬取引                                         38                                                         38                            38\n配当金                                                         人ム2, 391                                     人2, 391                      人へ2, 391\n自己株式の取得                                    9                    人へ1, 009                    A1. 000                    人へ1, 000\n自己株式の処分                                 AA47                         47                         ー                         ー\n非支配持分の取得                                  ムA79                                                       人へ79          人へ81         人へ160\n所有者との取引額合計             5       ムへ76     人ム2, 391      人へ962        ー     人3 424       人へ81     人へ3,505\n2023年11月30日残高                   656       13, 024       28,.996      へ1, 071            10       41,615            ー        41,615\n\n(単位 : 百万円)\n\n会社の\n資本金 。 資本利余金 利益和余金 自己株式    NM に人    次本合計\nする持分合計\n\n2024年3月1日残高                    659        13, 042        30.476       へ1, 071             4        43,110        43,110\n\n四半期利益                                                                  4, 428                                               4, 428           4, 428\n\nその他の包括利益                                                                                117            117            117\n\n四半期包括利益合計                        ー              ー          4, 428              ー             117          4. 545          4.545\n\n新株予約権の行使                      10              8                                                         18             18\n\n株式報酬取引                                         41                                                         41             41\n\n配当金                                                         人2, 465                                     人へ2, 465       へ2, 465\n\n自己株式の取得                                    4                    へ1, 005                    人へ1,001       人1, 001\n\n自己株式の処分                                 ム52                         52                         ー            ー\n\n所有者との取引額合計             10         1     人へ2, 465      人へ953        ー     人へ3.407     人へ3 407\n\n2024年11月30日残高                   669       13, 043       32.439      へ2.024           121       44, 248       44。 248\n\n想コメダホールディングス (3543) 2025年2月期 第3四半期決算短信\n\n(5) 要約四半期連結キャッシュ・フロー計算書\n\n(単位 : 百万円)\n前第 3 四半期連結果計期間 当第3   連結果計期間\n(自 2023年3月1日       (自 2024年3月1日\n至 2023年1月30日) 至 2024年11月30日)\n\n営業活動によるキャッシュ・フロー\n税引前四半期利益 6, 5996, 498\n減価償却費及び償却費                                                              1,198                           1, 144\n金融収益                                                              人41                       23\n金融費                                                              61                      223\n営業債権及びその他の債権の増減額 (へは増加)             人へ1.096          人1, 668\n差入保証金及び建設協力金の増減額 (へは増加)               人へ66            人へ96\n営業債務の増減額 (へは減少)                       310           270\n預り保証金及び建設協力金の増減額 (へは減少)               100            59\nその他の金融負債の増減額 (へは減少)                  2, 552          3, 031\nその他                               人141          人524\n小計 9, 4768, 914\n利息の受取額                              1            30\n利息の支払額                             人へ32           人へ41\n法人所得税等の支払額                          人へ2, 241          人2, 742\n法人所得税等の還付額                            487            470\n営業活動によるキャッシュ・フロー                   7, 691           6, 631\n\n投資活動によるキャッシュ・フロー\n定期預金の純増減 (へは増加)                          200            4,000\n有形固定資産の取得による支出                     人へ886          人747\n無形資産の取得による支出                        人へ75           人248\n投資有価証券の取得による支出                       人へ38            人13\nその他                                                                  66                        17\n投資活動によるキャッシュ・フロー                    人へ733          3, 009\n\n財務活動によるキャッシュ・フロー\n芽入金の返済による支出                         人へ1, 460          人1, 525\nリース負債の返済による支出                     人へ2, 809         人2, 968\n株式の発行による収入                          10            17\n自己株式の取得による支出                       人へ1.000          人1, 000\n親会社の所有者への配当金の支払額                  人へ2, 338         人へ2, 411\n\n連結の範囲の変更を伴わない子会社株式の取得\n\nによる支出                                                       2160                       ー\n財務活動によるキャッシュ・フロー                   人7, 757          人7, 887\n現金及び現金同等物に係る換算差額                       7           108\n現金及び現金同等物の増減額 (へは減少)                  人へ792          1, 861\n現金及び現金同等物の期首残高                      6, 681           7, 923\n現金及び現金同等物の四半期末残高                     5, 889          9, 784\n\n政コメダホールディングス (3543) 2025年2月期 第3四半期決算短1\n\nnl\n\n人朋\n\n半期連結財務諸表に関する注記事項\n企業の前提に関する注記)\n『項はありません。\n\n(会計方針の変更)\n\n当社グループが本要約四半期連結財務諾表において適用する重要性がある会計方針は、前連結会計年度の連結\n財務諸表において適用した会計方針と同一であります。\n\nなお、当第3 四半期連結果計期間の法人所得税費用は、見積年次実効税率を基に算定しております。\n\n(セグメント情報)\n当社グループは、喫茶店のFC事業の単一セグメントであるため、記載を省略しております。\n\n(売上収益)\n(単位 : 百万円)\n\n前第 3 四半期連結果計期間 | 当第 3 四半期連結果計期間\n\n(自 2023年3月1日     (自 2024年3月1日\n\n至 2023年11月30日) 至 2024年11月30日)\n外売                                                            23, 141                   25, 683\n直営店売上                              4 216          3, 789\n店舗開発収入                              834          1,006\nその他                                                           2, 718                    2, 934\n顧客との契約から認識した収益 計                30, 909          33, 412\nリースに係る収益                                      1, 211                1, 253\nその他の源泉から論識した収益 計                1, 211          1, 253\n合計 32, 12034, 665\n\n(1株当たり利益)\n前第 3 四半期連結果計期間 | 当第3四半期連結果計期間\n(自 2023年3月1日      (自 2024年3月1日\n至 2023年11月30日)      至 2024年1月30日)\n親会社の普通株主に帰属する四半期利益 (百万円)                       4, 492                     4, 428\n発行済普通株式の期中加重平均普通株式数 (株)                      45, 916, 215                  45, 565, 324\n希藻化効果のある株式数\nストック・オプション                                             33, 940                    18, 243\n希薄化効果調整後の期中加重平均普通株式数 (株)                    45, 950, 155                  45, 583, 567\n基本的 1 株当たり四半期利益 (円)                                97.83                  97.19\n希藻化後 1 株当たり四半期利益 (円)                                            97.76                           97.15"
  }
]