[
  {
    "title": "代表取締役の異動(退任)に関するお知らせ（15:30）",
    "timestamp": "",
    "clean_body": "各 位\nea\n必 い\n肖 日\nNF△SE\n2025年 4 月18日\n会社名:ウエルシアホールディングス株式会社\n社長執行役員最高業務執行責任者\n代表者名 : 代表取締役\n問合せ先 : 取締役兼執行役員人事・\n(コード番号 : 8141 東\n代表取締役の異動 (退任) に関するお知らせ\n当社は、2025年 4 月18日\nて決議いたしましたのでお\n1. 代表取締役の異動\n(1 ) 異動の理\n開催の取締役会に\n知らせいた します。\nおいて、下記のとおり、代表取締役の異動 (退有\n桐澤英明\n証プライ△)\n管理部門兼リスク管理担当\n高橋月\n(TEL : 03-5207-5878)\n回\nE) につい\n当社事業として、複雑化する市場変化により迅速に対応するため、若いリーダーを中心とした経\n営体制へ移行することが最善であると判断しました。\n(2 ) 退任予定の代表取締役\n氏名 現役職名\n池野共和 代表取締奥会長執行役員最高経営責任者\nE後にウエルシアホールディングス株式会社の会長に就任いたします。\n※池野隆光は、退人\n※この異動により、当社の代表取締役は、桐澤英明 1 名となる予定です。\n(3 ) 退任予定日\n2025年 5 月27日開催予定の第17\n定時株主\n総会の終結の時\n以",
    "tables": []
  },
  {
    "title": "2025年2月期決算説明会資料（8:59）",
    "timestamp": "",
    "clean_body": "2030年 地域N6:1の健康ステーションを目指して\n2030年のありたい姿\n2025年2月期 決算説明会\n2025年4月14日\nウエルシアホールディングス株式会社\n1. 2025年2月期 業績概要 3\n> 総括 4\n> 取組み 5\n> 業績 前期比・計画比 9\n> 業績 前年同期比期間 10\n> 業績 会社別 11\n> 既存店月次売上高伸長率 (国内) 12\n> 本目別売上高 13\n>本目別売上総利益率 14\n> 販売費及び一般管理費 15\n> 調剤部門実績 16\n> 従業上只数の状況 18\n> 出退店の状況 19\n2. 2026年2月期 業績予想 20\n> 計画の前提指標および重点施策 21\n> 業績予想 23\n> 出退店計画 24\n2025年2月期決算 2\n1. 業績概要\n・2024年3月15日付で、エクスチェンジを株式取得により完全子会社化いたしました。\n・ 2024年6月3日付で、とをしや薬局を株式取得により完全子会社化し、 同年9月1日付で\n当社の連結子会社のウエルシア薬局を存続会社として、 とをしや薬局を吸収合併いたしました。\n・2024年9月2日付で、ウェルバークを株式取得により完全子会社化いたしました。\n・2024年10月1日付で、ウエルシアパートナーズ (旧東電パートナーズ) を株式取得により完全子会社化いたしました。\nCopyright Welcia Holdings Co.,Ltd. 2025年2月期決算\n2025年2月期 総括\n売上高は調剤が堅調に推移。 販管融のコントロールが奏功し、\n滞業利益・経常利益ともに計画達成。\n・既存店売上の伸長、M L△による増収も、 還\n販管融では人材への積極的な投資による人件費増加などがあり、 増収減益。\n・親会社株主に帰属する当期純利益は、減損損失131億などと計上した影響。\n(単位:百万円/% )\n営業利益\n経常利益\n親会社株主に帰属する当期純利益\nCopyright Welcia Holdings Co.,Ltd. 2025年2月期決算\nプライベートブランドの取組み\n・PB物販売上高構成比は9.4%に拡大。 売上高は前期比11 7%と大きく伸長。\nP B物販売上高構成比 ブランド別売上高推移\n単位 :億\n1000\n二 - 946\nー 25.02期末 609\n285 3 っ H 750 704\n八ピコ△ 580\n14.9% 8\nーー 500\n0\nトップ人バリュ FY2022 FY2023 FY2024 FY2025\n26.1% 40.0% トップバリュ 八ピコ△ トップバリュ 時ウエルシアPB 目IT'S 画からだ・くらしWelcia\noN 。 ai ]\n5 に mn ー と「からだ・くらしWelcia」は、 商品の良さも認知され\nSKU拡大とともに、 前期比122%と大きく伸長。\nと トップバリュは品揃えの拡大と、 継続する物価上昇の中\nお手頃な価格で指示され、前期比1 18%と好調に推移。\nからだ・くらしWelcia販売SKU : 1 】 0) アイテ△\nCopyright Welcia Holdings Co.,Ltd. 2025年2月期決算 5\n| 判事業の取組み (地域No.1の健康ステーションに向けて) ” em\n調剤売上高は、 M&△および調剤併設推進やサービス拡充なとにより、 前年比110%と伸長。\n調剤併設推進と並行して、 地域に根差した取組みも推進。\n調剤売上高の推移 調剤における地域との接点\n単位 : 億円\n3.000 Me 2.825 っso% 月中 人9 婦店舗 唱 目\nーー売上構成比 2.569 放 4 薬剤師\nエー ～ 42\n。 っ |\n2,000\nう.282。 8.550:\n20.0% ャ 9\n1.000\n在宅訪問 内かかりつけ\n実施店舗 薬剤師\nー _ と ウエルシア薬局では、 調剤併設率88.6%\n> 調剤売上高は、毎期 2桁の伸長を続け あの\n2025年 2 月期は、売上高構成比 22% に拡大。 かかりつけ薬剤師、在宅訪問などHb域との接点を拡大。\n0 15.0%\nFY2021 FY2022 FY2023 FY2024 FY2025\nCopyright Welcia Holdings Co.,Ltd. 2025年2月期決算 6\n| 今期取組み進政 (W△ON POINTサーEス2)\n・ウエルシアメンバーW△ON POINTカード登録者数はぉ1,08オ4方人 ウルシァメンバーは、約1,386ヵ)\n・W△ON POINTカード提示率はウエルシアグルーブ全店で59%\n提示率および売上関与率 エリア別の提示率状況\n20% 689% 2024年3月\nW△ON提示率\nW△ON提示率\n60% 60.0%以上\n上 東北エリアは\n50% 大 709%超の提示率\n40%\n9の6\n6 Ws さ |\n△N、 語 財 導\n30% △ 1月2 月にかけて利用促進 7 が 2\n0\n24.03 24.05 24.08 24.11 25.02 <アー\nCp WON > 提示率60x以上のエリア拡大\n60%以上1,649店舗 (うち709%以上570店舗)\nと 2025年2月はキャンペーンなと施策効果もあり、\n提示率・関与率ともに大きく上昇。\nCopyright Welcia Holdings Co.,Ltd. 2025年2月期決算 7\n| 地域No.1の健康ステーションに向けて em秀\n・イオンタウン埋張西店にて、 2025年 3 月より「 未病・予防」に特化した\nヘルスケアサービスブース 「Care CaDSule (ヶァカプセル) 」 を設置。\n・管理栄養士が常駐し、 カウンセリングサービスのほか、 コンディショニングマシン設置、\nヘルスケアデバイスのショールーミング等、 健康をサポートするサービスを展開。\nConceDt\n未病から介護のプライマリケアサービスを提供する坦\n専門家で構成されるプライマリケアチー△が、 一人ひとりに合った\nヘルスクアサービスを提邊じ< 患者の心に寄り添う。\nーー\n軒 > 同店では、ウエルカフェや調剤室を併設しており、\n地域の人々の健康にフォーカスした取組みを進めている。\nCopyright Welcia Holdings Co.,Ltd. 2025年2月期決算 8\n| 業績 前期比計画比\n・計画比では、売上高は調剤が堅調に推移。 販管殴コントロールが奏功し営業利益・経常利益ともに計画達成。\n・ 前期比では、 既存店売上の伸長、 M &&△△による増収も、 賃上げ等による販管費増もあり増収減益。\n親会社株主に帰属する当期純利益は、減損損失131億など計上した影響。\n(単位:百万円ノ% )\n前期実績 実績\n構成比 前期比\n390,356 105.5\n353,947 108.3\n36,409 107.1\nE _ B 1 T D △ 67,306 5.5 58,919 4.5 62,348 4.9 92.6 105.8\n※EBITD△=営業利益減価償却費+のれん償却費\nCopyright Welcia Holdings Co.,Ltd. 2025年2月期決算 9\n| 業績 前年同期比期間\n・40Qでは、粗利率が大きく改善し営業利益・経常利益ともに増益に。\n上段 : 金額\n下段 : 構成比\n(単位:百万円プ% )\n24年】\n彰 ee at\n5月 「W△ON POINT」中心のサービス△移行\n23年】\nS月 人ON POINT」サービス導入\n4月\n5月 新型コロナウイルス 5 類感染 染症移行\n2025年2月期決算\nCopyright Welcia Holdings Co.,Ltd.\nジブ地震\n薬価改定後の交\n時情幸\nx渉結\n【2024年】\n9月 ウェルパークを完全子会社化\n10月 ウエルシアパートナーズを完全子会社化\n(東電パートナーズ)\n【2023年】\n9月 異例の暑さ続く\n10月 コロナ治療薬の全額公費負担終了\n【2024- 2025年】\n12月 ルン者人 1 医療機関あたり\n過去最多を記氏\n2月 日本海側を中心に記録的な大雪\n【2023-2024年】\n1月 令和6年能登半島地岩\n| 業績 会社史\n・ ウエルシア薬局はたばこ及び関連購買の減少、ポイントサービス変更等の影響により増収減益。\n・ コクミンは都市部の人流増加なとにより売上・粗利の伸長継続し、 増収増益。\n・ブプレひ\nまわりは2023年11月のポイントサービス切替えによる会員移行期の影響で減収。\n2024年11月以降の既存店売上高は、改善傾向。\n上段:金 額\n下段 : 構成比\n上\nウエルシアHD\n(連結)\n前期比\nウエル\nパーク\nウエルシア薬局\n丸大サクラ革薬局\nEUEln 前期比\n1.285,005| 105.6| 1,054,790 33,071\n売上総利益\n販売費及び|\nー般管理納\n営業利益\n経常利益\n親会社株主に\n帰 属す る\n当期純利益\nCopyright Welcia Holdings Co.,Ltd.\n2025年2月期決算\n11\nヽ ョーー トマエクア2 (\n| 既存店月次売上高伸長率 (国内)\n・ 通期既存店伸長率内訳 : 物販実績 0.29%% (計画 0.59%) 調剤実績 6.89% (計画 6.8%)\n通期実績 1.6% ーー\n(計画 1.89%)\nォー 実績 0.99% 一上 実績 1.99% 一 実績 1.1% 一一ょ> 実績 2.39%% 一一>\n(計画 2.19%) 6.196 (計画 2.49%) 6.2%\n\\\n売 人26 2 。 43% 42 4896 220 4.396\n上 ri\n高 4△1.196\n3月 4月 5月 6月 7月 8月 9月 10月 11月 12月 1月 2月\n客 2025年2月其\n2.596 ーー一容単価前年伸長\n数 - ーー一客数前年伸長\n・ 0.9%\n客\n^△0.8% 4△2.0%\n由 (リ\n価 。142。 41ラ66 ^1.0%\n人のーーーーーーーーーーーーーーーーーと\n3 月ポイントサービス変更告知 5 月W△ON POINT中心のポイントサービスへ変更\n当 花粉関連不調 猛署で季節品好調 残暑・暖冬で季節品不調 インフルエンザ流行\n期 健康食品不調 地震等の災害備蓄堪要増加 季節品需要回復\n前 | 四存関連雪増加 (セルフケア意識高まり) | 人流回復に伴いコロナ感染者増加 うるう征\n期 計粉関連好調 | 猛暑季節品好調 | 残置\"暖で地節品不調\nCopyright Welcia Holdings Co.,Ltd. 2025年2月期決算 12\n品目別売上高\n・ 物販においては医薬品はマスクなとの高要落ち着きによる影響。\n食品は単価上昇の影響や、 客数対策のチラシ販促商品なとが伸長。\n・ 調剤は併設推進による処方箋枚数増加なとの影響により1109%と伸長。\n(単位:百万円ノ% )\nウエルシアHD (連結) | \"ウエルシア薬局 フフレ0ひまわり 丸大サクラ二薬局 シミズ薬品\n前期比 前期比 前期比\n上段:金 額 |\n下段 : 構成比 |\nCopyright Welcia Holdings Co.,Ltd. 2025年2月期決算 13\n| 品目別売上総利益率\n・医薬品はインフルエンザ流行なとにより風邪関連商品の需要が増加し改善。\n化粧品はセルフ化粧品二\n・ 調剤は2024年4月薬価改定による\nウエルシアH D (連結) ウエルシア楽局 コクミン\n前期増減 前期増減 前期増減\nププレひまわり\n前期増減\n41.0| 4 1.0\n4 2.4\nが増加し改善。 食品の低下は客数対策のチラシ販促強化による\n影響があるも、 各種加算の取組みなとを進め4 0.19%\n旦有銀B\n京ク 響 o\n(単位:% )\nウェル | 丸大サクラ朱～ ッミズ薬品\nパー-ク |\n37.9\n31.9\n40.4\n31.8\n前期増減 前期増減\n0.5\n4 0.1\n0.1 33.4\n0.2 29.2\n4 2.8\n1.3\n0\n1.\n8\n.8\n.1\n.1\n.5\n24.9\n17.9\n22.5\n27.5\n41.1\n25.7\n16.4\n13.3\n25.5\n38.6\n4 0.2\n4 0.3\n28.7\n26.7\n4 0.2\nCopyright Welcia Holdings Co.,Ltd.\n2025年2月期決算\n0.3\n100.0\n28.8\n26.8\n4 zo △o5\n14\n| 販売費及び一般管理費\n・広告費は2024年 5 月のポイントサービス移行費用なとにより増加。\nその他は決済やめポイントに係る支払手数料や、新POSレジ導入費用による増加。\n(単位:百万円/% )\n上段:金 額 PP (連結) ウエルシア薬局 ( 2 丸大サクラエ薬局 シミズ薬品\nHL 前期比 前期比 前 前 前期比 前期比\n105.9| 14,852\n15\nCopyright Welcia Holdings Co.,Ltd. 2025年2月期決算\n| 調剤部門実績\n・売上高は、 併設推進による処方箋枚数増加等により継続して 2 桁伸長。\n・ 薬価改定の影絡を受け売上総利益率は低下。\n・ 調剤併設店舗数 : 2.282 (通期計画2,357) 調剤併設率 : 77.396 (通期計画78.6%)\n2022年2月期 2023年2月期 2024年2月期 2025年2月期\n前期比 前期比 前期比 前期比\n前期増減 前期増減 前期増減 前期増減\n| へ氏 | っ化\n束人ae \" 300店舗以上のチェーンストアの ma \" 薬価改定4月\n主な報酬改定等 | 毎年薬価改定に 調剤量本料の改定 \" 地域支援体制加算の経過措置終了 | レ 技術料改定 6 月\n*調剤併設率は、化粧品専門店を除いて算出しております\n* 2023年2月期の期首から、「収益認識に関する会計基準」を適用しております。\nCopyright Welcia Holdings Co.,Ltd. 2025年2月期決算\n16\n調剤部門実績 会社別\n・ 各社ウエルシアモデルの推進により、 調剤併設店舗数は今期127店舗増加 (併設率77.39%)\nの ウエルシア薬局 プフレひまわり | ウェルバーク| 丸大サクラ二薬局\n前期比 |, 前期比 |, 前期比 |, 前期比\n前期増減 前期増減 前期増減 前期増減\n前期比 |, 前期比\n\"25年2月期 前期増減 前期増減\n) | 282,548 110.0% 247.254 108.8% | 15.035 100.296 3.100 123.3%| 2.227 3.136 111.6%| 5,272 110.9%.\n27,359 109.69% 24.487 107.9% 874 101.5% 281 126.39% 265 339| 106.9%| 505 111.2%|\n10,327| 100.39% 10,.097 100.8%| 17,187 98.8%| 11.013 97.6%| 8.384| 9,246 104.49%| 10,439 99.7%|\n果 内 設 Ma 773 40. 7| 88.6 12 478 79 。 291 6.5| 21.0 471 2.0 e99 0.8|\n*調剤傍設率は、化粧 呈門店を除いて抽出しております。\nCopyright Welcia Holdings Co.,Ltd. 2025年2月期決算 17\n| 従業員数の状況\n2024年2月期\n第1四半期末 | 第2四半期末 | 第3四半期末\n第1四半期末\n2025年2月期\n第2四半期末 | 第3四半期末\n* 臨時従業員数 (8時間換算) は、10～3Qは各四半期、期末は通期の期中平均です。\n全 業 員数 1564g| 15494| 15355 16.611\n臨 時 従業 員 数\n(8換算人数 人) | 25.541| 26,423| 26,597\n薬 剤 師 数\n(在籍人数,人) 8,151 8,150 8,128 8,550\n+ 店舗当薬剤師数\n人 ) 。 。 。 。 2.90\n販 数 者 数 18,546 18,444 18,296 19,237 19,239 19,315 19,.896 20,735\nをコ 籍人 数,人) ? ? ? ?\n*薬剤師数・登録販売者数及び1店舗当薬剤師数・1店舗当登録販売者数は、化粧品専門店を除いて算出しております。\nCopyright Welcia Holdings Co.,Ltd. 2025年2月期決算\n18\n| 出退店の状況\n局\n子会社化または\n| 2024年 業譲渡に 半\n2月末 よる増減\n2,199\n8\n合併による\n【 一\n日\n|\nNNトー\nW\n|\nざ| |弟\nププブレひま\nエ\n(\nオ\nまこ\nン\n\"プレひまわり\nラ下薬～\n還\n| 一\n楽居\nル\nNIW\n7\n\\二\nS 2ばに\n4 名|時\n15\n13\n7\n5\n9\nェ 7\n国 内\n連 結\n北 道 7\n東 北 201\n関 東 1.373\n590\n531\n245\n州・沖 縄 54\n内 3.001\n全面改装\n前期実績 |\n81\nCopyright Welcia Holdings Co.,Ltd. 2025年2月期決算\n19\n2. 2026年2月期 業績予\n@ 株式会社ツウル八ホールディングスとの経営統合を予定しており、 2025年11月27日をもって上場廃止になる予定であ\nるため、 2026年 2 月期上期までの業績予想となります。\n@ 前期M&△については、 以下の通り。\n・2024年3月15日付で、エクスチェンジを株式取得により完全子会社化いたしました。\n2024年6月3日付で、とをしや薬局を株式取得により完全子会社化し、 同年9月1日付で、 当社の連結子会社の\nウエルシア薬局を存続会社として、とをしや薬局を吸収合併いたしました。\n・2024年9月2日付で、ウェルパークを株式取得により完全子会社化いたしました。\n・2024年10月1日付で、ウエルシアパートナーズ (I旧東電パートナーズ) を株式取得により完全子会社化いたしました\nCopyright Welcia Holdings Co.,Ltd.\n予想\n2025年2月期決算\n20\n| 2026年2月期 上期計画の前提指標および重点施策\n売上高 6,851億円 前期比 108.6%\n営業利益 205億円 前期比 108.696\n経常利益 227倍円 前期比 108.6%\n親会社株主に帰属する当期純利益 125億円 前期比 106.7%\n既存店売上高伸長率 3.09%\nうち物販 1.9%\nうち調剤 7.0%\n出店 29店 国内 29 海外 ー\n閉店 26店 国内 26 海外 ー\n期末店舗数 3,.016店 国内 3.004 海外 12\n調剤売上高 1.502億円 前期比 109.89%\n調剤人設店舗数 2,296店 併設率 77.8%\n新規開局 53店\n改装 (大型・中型改装) 179店 前期実績 39店\nCopyright Welcia Holdings Co.,Ltd. 2025年2月期決算 21\n|\n旬 新方針 ウエルシア2.0 に基づく取組み\n規模から利益への転換\n・ 既存店の強化・‥ 大型改装118店舗 中型改装61店舗\nしーー ょ 収益基盤の関東を中心として、 集中的に改装を実施。 地域特性に合わせた、 定番強化。\n・ グループ企業の収益改善へ向けた体制 連携強化\n・ 不採算店舗の整理、 深夜営業・24時間営業の見直し (営業時間の見直しは前期150店舗実施済)\n店舗の生産性向上のためのDX投資\n・ 全店への小型タプレット導入 (インカ△・チャットによる指示など業務効率化)\n・ 自動発注のカテゴリー発注曜日制御による、 物流と店舗作業の効率化\n・ 電子棚札の導入開始 (ブライスカード等の付替え作業の削減。 下期100店舗で導入予定)\nウエルシアのプライベートブランド\n・ PB物販売上高構成比目標・‥・ 11.0%\nウエルシア独自PBの品そろえ拡充。\nマーケティング (顧客基盤の強化と拡天\n・ TIDデータ活用によるOne to Oneマーケティング推進 (イオングループとの連携・△t活用による販促開始)\n・ ウエルシアアプリの刷新・リテールメディア販売の拡大 (店舗サイネージ、 アプリ、 SNS等)\nCopyright Welcia Holdings Co.,Ltd. 2025年2月期決算 22\n| 業績予想\n(単位:百万円/% )\n前期実績\n685,100 100.0 630,585 108.6 54,514\n150,200 本 136,818 109.8 13,381\n既 存 店 伸 長 率 3.0\nCopyright Welcia Holdings Co.,Ltd. 2025年2月期決算 23\n調剤併設店\n調剤併設率 73%ト| よー R((了(了WV 77.8%\n*調剤併設率は、化粧品専門店を除いて算出しております。\nCopyright Welcia Holdings Co.,Ltd. 2025年2月期決算 24\n| IRに関する免責事項\nCopyright Welcia Holdings Co.,Ltd.\n当資料は、 投資家の皆様にウエルシアホールディングス株式会社への理解を深めていただくことを目的として、\n経営や財務に関する情報を提供するものです。また、 以下の点を～了解の上、～覧ください。\n本資料に含まれる業績については、 監査法人による会計監査を受けておりません。\n業績見通し等は作成時点において、 当社が予測しうる範囲内で作成したものです。\n記載の業績見通し等とは異なる結果を生じ得るリスクを含んでおりますことを～承知ください。\n投資に関する決定は投資家～自身の～判断において行われるようお願いいたします。\n掲載内容について細心の注意を払っておりますが、 不可抗力によって情報に誤りを生ずる\n可能性も～ざいますので、～注意下さい。\n2025年2月期決算\n25",
    "tables": [
      "2025年2月期 決算説明会\n2025年4月14日\nウエルシアホールディングス株式会社\n1. 2025年2月期 業績概要 3\n> 総括 4\n> 取組み 5\n> 業績 前期比・計画比 9\n> 業績 前年同期比期間 10\n> 業績 会社別 11\n> 既存店月次売上高伸長率 (国内) 12\n> 本目別売上高 13\n>本目別売上総利益率 14\n> 販売費及び一般管理費 15\n> 調剤部門実績 16\n> 従業上只数の状況 18\n> 出退店の状況 19\n2. 2026年2月期 業績予想 20\n> 計画の前提指標および重点施策 21\n> 業績予想 23\n> 出退店計画 24\n2025年2月期決算 2\n1. 業績概要\n・2024年3月15日付で、エクスチェンジを株式取得により完全子会社化いたしました。\n・ 2024年6月3日付で、とをしや薬局を株式取得により完全子会社化し、 同年9月1日付で\n当社の連結子会社のウエルシア薬局を存続会社として、 とをしや薬局を吸収合併いたしました。\n・2024年9月2日付で、ウェルバークを株式取得により完全子会社化いたしました。\n・2024年10月1日付で、ウエルシアパートナーズ (旧東電パートナーズ) を株式取得により完全子会社化いたしました。\nCopyright Welcia Holdings Co.,Ltd. 2025年2月期決算\n2025年2月期 総括\n売上高は調剤が堅調に推移。 販管融のコントロールが奏功し、\n滞業利益・経常利益ともに計画達成。\n・既存店売上の伸長、M L△による増収も、 還\n販管融では人材への積極的な投資による人件費増加などがあり、 増収減益。\n・親会社株主に帰属する当期純利益は、減損損失131億などと計上した影響。\n(単位:百万円/% )\n営業利益\n経常利益\n親会社株主に帰属する当期純利益\nCopyright Welcia Holdings Co.,Ltd. 2025年2月期決算\nプライベートブランドの取組み\n・PB物販売上高構成比は9.4%に拡大。 売上高は前期比11 7%と大きく伸長。\nP B物販売上高構成比 ブランド別売上高推移\n単位 :億\n1000\n二 - 946\nー 25.02期末 609\n285 3 っ H 750 704\n八ピコ△ 580\n14.9% 8\nーー 500\n0\nトップ人バリュ FY2022 FY2023 FY2024 FY2025\n26.1% 40.0% トップバリュ 八ピコ△ トップバリュ 時ウエルシアPB 目IT'S 画からだ・くらしWelcia\noN 。 ai ]\n5 に mn ー と「からだ・くらしWelcia」は、 商品の良さも認知され\nSKU拡大とともに、 前期比122%と大きく伸長。\nと トップバリュは品揃えの拡大と、 継続する物価上昇の中\nお手頃な価格で指示され、前期比1 18%と好調に推移。\nからだ・くらしWelcia販売SKU : 1 】 0) アイテ△\nCopyright Welcia Holdings Co.,Ltd. 2025年2月期決算 5\n| 判事業の取組み (地域No.1の健康ステーションに向けて) ” em\n調剤売上高は、 M&△および調剤併設推進やサービス拡充なとにより、 前年比110%と伸長。\n調剤併設推進と並行して、 地域に根差した取組みも推進。\n調剤売上高の推移 調剤における地域との接点\n単位 : 億円\n3.000 Me 2.825 っso% 月中 人9 婦店舗 唱 目\nーー売上構成比 2.569 放 4 薬剤師\nエー ～ 42\n。 っ |\n2,000\nう.282。 8.550:\n20.0% ャ 9\n1.000\n在宅訪問 内かかりつけ\n実施店舗 薬剤師\nー _ と ウエルシア薬局では、 調剤併設率88.6%\n> 調剤売上高は、毎期 2桁の伸長を続け あの\n2025年 2 月期は、売上高構成比 22% に拡大。 かかりつけ薬剤師、在宅訪問などHb域との接点を拡大。\n0 15.0%\nFY2021 FY2022 FY2023 FY2024 FY2025\nCopyright Welcia Holdings Co.,Ltd. 2025年2月期決算 6\n| 今期取組み進政 (W△ON POINTサーEス2)\n・ウエルシアメンバーW△ON POINTカード登録者数はぉ1,08オ4方人 ウルシァメンバーは、約1,386ヵ)\n・W△ON POINTカード提示率はウエルシアグルーブ全店で59%\n提示率および売上関与率 エリア別の提示率状況\n20% 689% 2024年3月\nW△ON提示率\nW△ON提示率\n60% 60.0%以上\n上 東北エリアは\n50% 大 709%超の提示率\n40%\n9の6\n6 Ws さ |\n△N、 語 財 導\n30% △ 1月2 月にかけて利用促進 7 が 2\n0\n24.03 24.05 24.08 24.11 25.02 <アー\nCp WON > 提示率60x以上のエリア拡大\n60%以上1,649店舗 (うち709%以上570店舗)\nと 2025年2月はキャンペーンなと施策効果もあり、\n提示率・関与率ともに大きく上昇。\nCopyright Welcia Holdings Co.,Ltd. 2025年2月期決算 7\n| 地域No.1の健康ステーションに向けて em秀\n・イオンタウン埋張西店にて、 2025年 3 月より「 未病・予防」に特化した\nヘルスケアサービスブース 「Care CaDSule (ヶァカプセル) 」 を設置。\n・管理栄養士が常駐し、 カウンセリングサービスのほか、 コンディショニングマシン設置、\nヘルスケアデバイスのショールーミング等、 健康をサポートするサービスを展開。\nConceDt\n未病から介護のプライマリケアサービスを提供する坦\n専門家で構成されるプライマリケアチー△が、 一人ひとりに合った\nヘルスクアサービスを提邊じ< 患者の心に寄り添う。\nーー\n軒 > 同店では、ウエルカフェや調剤室を併設しており、\n地域の人々の健康にフォーカスした取組みを進めている。\nCopyright Welcia Holdings Co.,Ltd. 2025年2月期決算 8\n| 業績 前期比計画比\n・計画比では、売上高は調剤が堅調に推移。 販管殴コントロールが奏功し営業利益・経常利益ともに計画達成。\n・ 前期比では、 既存店売上の伸長、 M &&△△による増収も、 賃上げ等による販管費増もあり増収減益。\n親会社株主に帰属する当期純利益は、減損損失131億など計上した影響。\n(単位:百万円ノ% )\n前期実績 実績\n構成比 前期比\n390,356 105.5\n353,947 108.3\n36,409 107.1\nE _ B 1 T D △ 67,306 5.5 58,919 4.5 62,348 4.9 92.6 105.8\n※EBITD△=営業利益減価償却費+のれん償却費\nCopyright Welcia Holdings Co.,Ltd. 2025年2月期決算 9\n| 業績 前年同期比期間\n・40Qでは、粗利率が大きく改善し営業利益・経常利益ともに増益に。\n上段 : 金額\n下段 : 構成比\n(単位:百万円プ% )\n24年】\n彰 ee at\n5月 「W△ON POINT」中心のサービス△移行\n23年】\nS月 人ON POINT」サービス導入\n4月\n5月 新型コロナウイルス 5 類感染 染症移行\n2025年2月期決算\nCopyright Welcia Holdings Co.,Ltd.\nジブ地震\n薬価改定後の交\n時情幸\nx渉結\n【2024年】\n9月 ウェルパークを完全子会社化\n10月 ウエルシアパートナーズを完全子会社化\n(東電パートナーズ)\n【2023年】\n9月 異例の暑さ続く\n10月 コロナ治療薬の全額公費負担終了\n【2024- 2025年】\n12月 ルン者人 1 医療機関あたり\n過去最多を記氏\n2月 日本海側を中心に記録的な大雪\n【2023-2024年】\n1月 令和6年能登半島地岩\n| 業績 会社史\n・ ウエルシア薬局はたばこ及び関連購買の減少、ポイントサービス変更等の影響により増収減益。\n・ コクミンは都市部の人流増加なとにより売上・粗利の伸長継続し、 増収増益。\n・ブプレひ\nまわりは2023年11月のポイントサービス切替えによる会員移行期の影響で減収。\n2024年11月以降の既存店売上高は、改善傾向。\n上段:金 額\n下段 : 構成比\n上\nウエルシアHD\n(連結)\n前期比\nウエル\nパーク\nウエルシア薬局\n丸大サクラ革薬局\nEUEln 前期比\n1.285,005| 105.6| 1,054,790 33,071\n売上総利益\n販売費及び|\nー般管理納\n営業利益\n経常利益\n親会社株主に\n帰 属す る\n当期純利益\nCopyright Welcia Holdings Co.,Ltd.\n2025年2月期決算\n11\nヽ ョーー トマエクア2 (\n| 既存店月次売上高伸長率 (国内)\n・ 通期既存店伸長率内訳 : 物販実績 0.29%% (計画 0.59%) 調剤実績 6.89% (計画 6.8%)\n通期実績 1.6% ーー\n(計画 1.89%)\nォー 実績 0.99% 一上 実績 1.99% 一 実績 1.1% 一一ょ> 実績 2.39%% 一一>\n(計画 2.19%) 6.196 (計画 2.49%) 6.2%\n\\\n売 人26 2 。 43% 42 4896 220 4.396\n上 ri\n高 4△1.196\n3月 4月 5月 6月 7月 8月 9月 10月 11月 12月 1月 2月\n客 2025年2月其\n2.596 ーー一容単価前年伸長\n数 - ーー一客数前年伸長\n・ 0.9%\n客\n^△0.8% 4△2.0%\n由 (リ\n価 。142。 41ラ66 ^1.0%\n人のーーーーーーーーーーーーーーーーーと\n3 月ポイントサービス変更告知 5 月W△ON POINT中心のポイントサービスへ変更\n当 花粉関連不調 猛署で季節品好調 残暑・暖冬で季節品不調 インフルエンザ流行\n期 健康食品不調 地震等の災害備蓄堪要増加 季節品需要回復\n前 | 四存関連雪増加 (セルフケア意識高まり) | 人流回復に伴いコロナ感染者増加 うるう征\n期 計粉関連好調 | 猛暑季節品好調 | 残置\"暖で地節品不調\nCopyright Welcia Holdings Co.,Ltd. 2025年2月期決算 12\n品目別売上高\n・ 物販においては医薬品はマスクなとの高要落ち着きによる影響。\n食品は単価上昇の影響や、 客数対策のチラシ販促商品なとが伸長。\n・ 調剤は併設推進による処方箋枚数増加なとの影響により1109%と伸長。\n(単位:百万円ノ% )\nウエルシアHD (連結) | \"ウエルシア薬局 フフレ0ひまわり 丸大サクラ二薬局 シミズ薬品\n前期比 前期比 前期比\n上段:金 額 |\n下段 : 構成比 |\nCopyright Welcia Holdings Co.,Ltd. 2025年2月期決算 13\n| 品目別売上総利益率\n・医薬品はインフルエンザ流行なとにより風邪関連商品の需要が増加し改善。\n化粧品はセルフ化粧品二\n・ 調剤は2024年4月薬価改定による\nウエルシアH D (連結) ウエルシア楽局 コクミン\n前期増減 前期増減 前期増減\nププレひまわり\n前期増減\n41.0| 4 1.0\n4 2.4\nが増加し改善。 食品の低下は客数対策のチラシ販促強化による\n影響があるも、 各種加算の取組みなとを進め4 0.19%\n旦有銀B\n京ク 響 o\n(単位:% )\nウェル | 丸大サクラ朱～ ッミズ薬品\nパー-ク |\n37.9\n31.9\n40.4\n31.8\n前期増減 前期増減\n0.5\n4 0.1\n0.1 33.4\n0.2 29.2\n4 2.8\n1.3\n0\n1.\n8\n.8\n.1\n.1\n.5\n24.9\n17.9\n22.5\n27.5\n41.1\n25.7\n16.4\n13.3\n25.5\n38.6\n4 0.2\n4 0.3\n28.7\n26.7\n4 0.2\nCopyright Welcia Holdings Co.,Ltd.\n2025年2月期決算\n0.3\n100.0\n28.8\n26.8\n4 zo △o5\n14\n| 販売費及び一般管理費\n・広告費は2024年 5 月のポイントサービス移行費用なとにより増加。\nその他は決済やめポイントに係る支払手数料や、新POSレジ導入費用による増加。\n(単位:百万円/% )\n上段:金 額 PP (連結) ウエルシア薬局 ( 2 丸大サクラエ薬局 シミズ薬品\nHL 前期比 前期比 前 前 前期比 前期比\n105.9| 14,852\n15\nCopyright Welcia Holdings Co.,Ltd. 2025年2月期決算\n| 調剤部門実績\n・売上高は、 併設推進による処方箋枚数増加等により継続して 2 桁伸長。\n・ 薬価改定の影絡を受け売上総利益率は低下。\n・ 調剤併設店舗数 : 2.282 (通期計画2,357) 調剤併設率 : 77.396 (通期計画78.6%)\n2022年2月期 2023年2月期 2024年2月期 2025年2月期\n前期比 前期比 前期比 前期比\n前期増減 前期増減 前期増減 前期増減\n| へ氏 | っ化\n束人ae \" 300店舗以上のチェーンストアの ma \" 薬価改定4月\n主な報酬改定等 | 毎年薬価改定に 調剤量本料の改定 \" 地域支援体制加算の経過措置終了 | レ 技術料改定 6 月\n*調剤併設率は、化粧品専門店を除いて算出しております\n* 2023年2月期の期首から、「収益認識に関する会計基準」を適用しております。\nCopyright Welcia Holdings Co.,Ltd. 2025年2月期決算\n16\n調剤部門実績 会社別\n・ 各社ウエルシアモデルの推進により、 調剤併設店舗数は今期127店舗増加 (併設率77.39%)\nの ウエルシア薬局 プフレひまわり | ウェルバーク| 丸大サクラ二薬局\n前期比 |, 前期比 |, 前期比 |, 前期比\n前期増減 前期増減 前期増減 前期増減\n前期比 |, 前期比\n\"25年2月期 前期増減 前期増減\n) | 282,548 110.0% 247.254 108.8% | 15.035 100.296 3.100 123.3%| 2.227 3.136 111.6%| 5,272 110.9%.\n27,359 109.69% 24.487 107.9% 874 101.5% 281 126.39% 265 339| 106.9%| 505 111.2%|\n10,327| 100.39% 10,.097 100.8%| 17,187 98.8%| 11.013 97.6%| 8.384| 9,246 104.49%| 10,439 99.7%|\n果 内 設 Ma 773 40. 7| 88.6 12 478 79 。 291 6.5| 21.0 471 2.0 e99 0.8|\n*調剤傍設率は、化粧 呈門店を除いて抽出しております。\nCopyright Welcia Holdings Co.,Ltd. 2025年2月期決算 17\n| 従業員数の状況\n2024年2月期\n第1四半期末 | 第2四半期末 | 第3四半期末\n第1四半期末\n2025年2月期\n第2四半期末 | 第3四半期末\n* 臨時従業員数 (8時間換算) は、10～3Qは各四半期、期末は通期の期中平均です。\n全 業 員数 1564g| 15494| 15355 16.611\n臨 時 従業 員 数\n(8換算人数 人) | 25.541| 26,423| 26,597\n薬 剤 師 数\n(在籍人数,人) 8,151 8,150 8,128 8,550\n+ 店舗当薬剤師数\n人 ) 。 。 。 。 2.90\n販 数 者 数 18,546 18,444 18,296 19,237 19,239 19,315 19,.896 20,735\nをコ 籍人 数,人) ? ? ? ?\n*薬剤師数・登録販売者数及び1店舗当薬剤師数・1店舗当登録販売者数は、化粧品専門店を除いて算出しております。\nCopyright Welcia Holdings Co.,Ltd. 2025年2月期決算\n18\n| 出退店の状況\n局\n子会社化または\n| 2024年 業譲渡に 半\n2月末 よる増減\n2,199\n8\n合併による\n【 一\n日\n|\nNNトー\nW\n|\nざ| |弟\nププブレひま\nエ\n(\nオ\nまこ\nン\n\"プレひまわり\nラ下薬～\n還\n| 一\n楽居\nル\nNIW\n7\n\\二\nS 2ばに\n4 名|時\n15\n13\n7\n5\n9\nェ 7\n国 内\n連 結\n北 道 7\n東 北 201\n関 東 1.373\n590\n531\n245\n州・沖 縄 54\n内 3.001\n全面改装\n前期実績 |\n81\nCopyright Welcia Holdings Co.,Ltd. 2025年2月期決算\n19\n2. 2026年2月期 業績予\n@ 株式会社ツウル八ホールディングスとの経営統合を予定しており、 2025年11月27日をもって上場廃止になる予定であ\nるため、 2026年 2 月期上期までの業績予想となります。\n@ 前期M&△については、 以下の通り。\n・2024年3月15日付で、エクスチェンジを株式取得により完全子会社化いたしました。\n2024年6月3日付で、とをしや薬局を株式取得により完全子会社化し、 同年9月1日付で、 当社の連結子会社の\nウエルシア薬局を存続会社として、とをしや薬局を吸収合併いたしました。\n・2024年9月2日付で、ウェルパークを株式取得により完全子会社化いたしました。\n・2024年10月1日付で、ウエルシアパートナーズ (I旧東電パートナーズ) を株式取得により完全子会社化いたしました\nCopyright Welcia Holdings Co.,Ltd.\n予想\n2025年2月期決算\n20\n| 2026年2月期 上期計画の前提指標および重点施策\n売上高 6,851億円 前期比 108.6%\n営業利益 205億円 前期比 108.696\n経常利益 227倍円 前期比 108.6%\n親会社株主に帰属する当期純利益 125億円 前期比 106.7%\n既存店売上高伸長率 3.09%\nうち物販 1.9%\nうち調剤 7.0%\n出店 29店 国内 29 海外 ー\n閉店 26店 国内 26 海外 ー\n期末店舗数 3,.016店 国内 3.004 海外 12\n調剤売上高 1.502億円 前期比 109.89%\n調剤人設店舗数 2,296店 併設率 77.8%\n新規開局 53店\n改装 (大型・中型改装) 179店 前期実績 39店\nCopyright Welcia Holdings Co.,Ltd. 2025年2月期決算 21\n|\n旬 新方針 ウエルシア2.0 に基づく取組み\n規模から利益への転換\n・ 既存店の強化・‥ 大型改装118店舗 中型改装61店舗\nしーー ょ 収益基盤の関東を中心として、 集中的に改装を実施。 地域特性に合わせた、 定番強化。\n・ グループ企業の収益改善へ向けた体制 連携強化\n・ 不採算店舗の整理、 深夜営業・24時間営業の見直し (営業時間の見直しは前期150店舗実施済)\n店舗の生産性向上のためのDX投資\n・ 全店への小型タプレット導入 (インカ△・チャットによる指示など業務効率化)\n・ 自動発注のカテゴリー発注曜日制御による、 物流と店舗作業の効率化\n・ 電子棚札の導入開始 (ブライスカード等の付替え作業の削減。 下期100店舗で導入予定)\nウエルシアのプライベートブランド\n・ PB物販売上高構成比目標・‥・ 11.0%\nウエルシア独自PBの品そろえ拡充。\nマーケティング (顧客基盤の強化と拡天\n・ TIDデータ活用によるOne to Oneマーケティング推進 (イオングループとの連携・△t活用による販促開始)\n・ ウエルシアアプリの刷新・リテールメディア販売の拡大 (店舗サイネージ、 アプリ、 SNS等)\nCopyright Welcia Holdings Co.,Ltd. 2025年2月期決算 22\n| 業績予想\n(単位:百万円/% )\n前期実績\n685,100 100.0 630,585 108.6 54,514\n150,200 本 136,818 109.8 13,381\n既 存 店 伸 長 率 3.0\nCopyright Welcia Holdings Co.,Ltd. 2025年2月期決算 23\n調剤併設店\n調剤併設率 73%ト| よー R((了(了WV 77.8%\n*調剤併設率は、化粧品専門店を除いて算出しております。\nCopyright Welcia Holdings Co.,Ltd. 2025年2月期決算 24\n| IRに関する免責事項\nCopyright Welcia Holdings Co.,Ltd.\n当資料は、 投資家の皆様にウエルシアホールディングス株式会社への理解を深めていただくことを目的として、\n経営や財務に関する情報を提供するものです。また、 以下の点を～了解の上、～覧ください。\n本資料に含まれる業績については、 監査法人による会計監査を受けておりません。\n業績見通し等は作成時点において、 当社が予測しうる範囲内で作成したものです。\n記載の業績見通し等とは異なる結果を生じ得るリスクを含んでおりますことを～承知ください。\n投資に関する決定は投資家～自身の～判断において行われるようお願いいたします。\n掲載内容について細心の注意を払っておりますが、 不可抗力によって情報に誤りを生ずる\n可能性も～ざいますので、～注意下さい。\n2025年2月期決算\n25"
    ]
  },
  {
    "title": "イオン株式会社、株式会社ツルハホールディングス及びウエルシアホールディングス株式会社による資本業務提携に係る最終契約締結に関するお知らせ（16:30）",
    "timestamp": "",
    "clean_body": "各 位\nCU\nPe\nbs weン\nF△SF\n2025年 4 月11日\n会社名 イオン株式会社\n代表者名 取締役兼代表執行役社長 吉 昭夫\n(コード番号 : 8267 東証プライ△)\n問合せ先 執行役財務・経営管理担当 江川 敬明\n(TEL. 043-212-6042)\n会社名 株式会社ツルハホールディングス\n代表者名 代表取締役社長 稚羽 順\n(コード番号 : 3391 東証プライ△)\n問合せ先 執行役員人事総務本部長 尾島 徳仁\n(TE工. 011-783-2755)\n会社名 ウエルシアホールディングス株式会社\n代表者名 代表取締役兼社長執行役員最高業務執行責仕者\n桐澤 英明\n(コード番号 : 3141 東証プライ△)\n問合せ先 取締役兼執行役員人事・管理部門兼リスク管理担当\n高橋 康司\n(TEL. 03-5207-5878)\nイオン株式会社、株式会社ツルハホールディングス及びウエルシアホールディングス\n株式会社による資本業務提携に係る最終閥約締結に関するお知らせ\nイオン株式会社 (以下「イオン」といいます。)、株式会社ツウルハホールディングス (以]\n「ツルバハHD」\nアHD」といいます。) は、2024 年2月 28 日付「株式会社ツルハホールディングス、イオ\nン株式会社及びウエルシアホールディングス株式会社との資本業務提携、並びに株式会社\nツルハホールディングスにおける主要株主及び主要株主である筆頭株主の異動に関するお\n知らせ」 にてお知らせいたしましたとおり、日本のみならず△SE△N (東南アジア諸国財\nといいます。) 及びウエルシアホールディングス株式会社 (以下「ウエルシ\n遇\n合) をはじめとするグローバル規模において、人々の未病、 予防、治療に従事し、健康寿命\nの延伸に貢献することにより、地域生活者のより高次なヘルス和&ウエルネスの実現を目的\nとしたツルハHD及びウエルシアHDの経営統合 (以下「本経営統合」 といいます。) を含\nむイオン、ツノ\nます。) の協議\nレハHD及びウエルシアHDの資本業務提携 (以下「本資本業務提携」といい\nを開始することに合意し、同日付で、資本業務提携下約を締結いたしました。\nその後、イオン、 ツルハHD及びウエルシア HDは、 本経営統合を含む本資本業務提携の\n具体的な方法及び条件、並びに実現可能なシナジーの具体的な内容及びその効果について\n検討・協議を進め、本日、本資本業務提携に係る最終契約 (以下 「本資本業務提携最終契約」\nといいます。)\nつきまして6\nなお、本経営\n換 (下記「I.\nを締結することを決定いたしました。\nま、以下のとおりお知らせいたします。\n営統合の一環と して行われるツルハHD及びウエルシアHDによる本株式交\n本資本業務提携最終契約に定める資本業務提携の内容」の「(1) 資本提携\nの内容」にて定義されます。) の詳細については、ツルハHD及びウエルシアHDによる本\n1\n日付「株式会社ツウルハホールディングスとウェエ/\n合に関する株式交換契約の締結に関するお知らせ」を～参照ください。 また、 本資本業務提\n携の一環として、本株式交換の効力発生により、\n(以下「ツルハHD株式」といいます。) の議決\n約に定める資本業務提携の\nイオンによる本公開買付け\n容」の「(1) 資本提携の内\n内容」の「(1) 資本\nです。) が 50.9%%とならなかった場合に、 本株式交換の効力発4\nシアホールディングス株式会社の経営統\nイオンが保有するツルハHD の普通株式\n枚割合 (下記「I. 本資本業務提携最終契\n提携の内容」にて定義されます。以下同じ\nE日以後速やかに実施される\n(下記「II. 本資本業務提携最終契約に定める資本業務提携の内\n容」にて定義されま3\nす。) の開始予定及びツルハHDによる本公\n開買付けの開始予定に係る意見表明の詳細については、イオンが本日付で公表した「株式会\n社ツルハホールディングス (証券コード : 3391) に対する公開買付けの開始予定に関するお\n知らせ」 及びツルハHDが本日付で公表 した「イオン株式会社による当社株式に対する公開\n買付けの開始予定に関する意見表明のお知らせ」 をそれぞれ～参照ください。\nI. 資本業務提携の目的\nイオン、ツルハ是D及びウエルシアHDは、 今後、国内において、\n記\n医療、健康の地域格差\nが一層拡大していくとの共通認識を有しています。 地方においては、 過疎化が進むにつれ、\nドラッグストアにおいて生鮮食品や雑貨を含むワンストップの買い\n物需要が増加すること\nや、医療、 介護、 行政等の機能の付加がさらに求められるようになると想定されます。 本経\n営統合を含む本資本業務提携に』\nが保有する店舗網、ノウハウ、調\nことにより、\nなります。\n△SE△Nにおいても、国内と同様に高齢化が\nが少なくありません。こ う\nアが果たす役割は、 ますます本\nびにイオンの子会社及び関連会社をいいます。 以下同\nツルハHD並びにツルハHD の子会社及び関連会社 (じ\nシアHD並びにウエルシア是Dの子会視\nといいます。) は含まれないものと します。) が有する中\nすることにより、ツルハHD及びウエルシア\nウエノ\n的資源、 調達網等を活\nした地域における人々の健\n要になっていくと想定されます。 イオングループ (イオンバ\nじです。 なお、イオングループには、\n下「ツルハグループ」 といいます。) 、\n上及び関連会社 (以下「ウエルシアグループ」\n進む地域や、健有\n達網、 物流システ△、 顧客デ\nこうした新たな需要に応えることのできる、新たな業態の開発や出店が可能\nトって獲得する圧倒的なスケールメリット、各社グループ\nク基盤等を最大限活\nする\n保険制度が未発達な地域\n奉命の延伸のために\nに加速することができると考えています。\n玉|\nオン、 ツルハHD及びウエルシアHDは、 本経営統合を含む本資\n活者のより高次なヘルス&&ウエルネスを実現することにつながると\nバラッグス\n・△SE△Nにおける店舗網、人\nHDの事業展開を一気\n本業務提携が、 地域生\n間断し、本資本業務提\n携最終契約の締結を決定しました。 これにより、日本最大のドラッグストア連合体を創成し、\n競争力の獲得、アジアNo. 1 のグローバル企業への成】\n業員の限りない成長機会を創出していきます。\nI. 本資本業務提携最終契約に定める資本業務提携の内容\n(1 ) 資本提携の内容\n長を目指すとともに、そこで働く従\nイオン、ツルハHD及びウエルシアHDは、本資本業務提携と して、以下の取引を実\n施します。\nこれらの各取引により、 ウェルシアHDはツルハHD の完全子会社となり、\n両社合わ\nせて売上高 2 兆円超、店舗数約 5, 500 を擁する日本最大のドラッグストア連合体を創成\nし、競争力の獲得、アジアN o. 1 のグローバル企業への成長を目指すとともに、そこ\nで働く従業員の限りない成長機会を創出することを目指します。また、イオンは、自ら\n2\nが保有するツルハHD株式に係る議決権の数の割合 (以下「議決権割合」 といいます。)\nが 50.99%となるよう、ツルハHHD株式を取得することで、 ツルハHDを連結子会社とす\n会社化」といいます。) とともに、 ツルハHDは、イオングループの\nる (以下「本連結\nヘルス&ウエルネ\nス事業を牽引する中核子会社となります。\n① イオンは、 法令等に基づき必要なクリアランス・許認可等を取得したこと等の条\nることを前提に、野村誇券株式会社よりツルハHD株式 3, 530, 000 株\nす。これにより、イオンが保有するツルハHD株式は、 既に保有して\nいるツルハHD株式 9, 675, 200 株と合わせて 13, 205, 200 株 (所有割合 (注1)\nとなり、ツルハHHDはイオンの持分法適用関連会社となる予定です。\nルハHD及びウエルシアHDが締結した、ツルハHD を株式交換完全\n親会社とし、ウエルシアHHDを株式交換完全子会社とする株式交換 (以下「本株\n件が充足す\nを取得しま\nは 26.83%)\n② 本日付でツ\n式交換」と\nづき、法令\n当事会社の\n提に、2025 有\nなお、 ツルハHDは、2025 年9月1日を効力発生日として、 ツルハ\nを5株とす\n③ 本株式交換\n50.9%とな\nに、 ツルハ\nするとともに\n決権割合が\nいいます。) に係る契約 (以下 「本株式交換契約」 といい\nます。) に基\n等に基づき必要なクリアランス・主認可等を取得したこと、及び、各\n株主総会における承認を取得したこと等の条件が充足することを前\n年12月1日を効力発生日 (予定) と して、 本株式交換を実施します。\nD株式1 株\nる株式分割 (以下「本株式分割」 といいます。) を行う予定です。\nの効力発生により、イオンが保有するツルハHD株式の議決権割合が\nらなかった場合には、イオンは、 本株式交換の効力発生日以後速やか\nHD株式への公開買付け (以下「本公開買付け」といいま\nす。) を開始\n、 本公開買付けの決済を行い、イオンが保有するツルハ\n50.99%となるよう、 ツルハHD株式を取得します。 なお、\nけは 2026\n④ 本公開買付\n別途協議し、合\n年1月に完了することを見込んでおります。\nD株式の議\n本公開買付\nけの決済後において、イオンが保有するツルハHD株式の議決権割合\nが 50. 9%となちらななかった場合に は、イオン及びツルハHD は、その対応について\n意により決定します。\n(注1) 「所有割合」 とは、ツルハHDが 2025 年4月 11 日に提出 した 2025 年 2 月期決\n算短信\nされた\n[日本基準〕 (連結) (以下「ツルハHD決算短信」といいま\n2025 年2 月 28 日現在の発行済株式総数 (49, 557, 068 株) に\nす。) に記載\n、ツルハHH\nDが同日現在残條するものと報告した新株予約権 5,149 個 (以下「本新株予約\n権」といいます。) (注2) の目的であるツルハHD株式数の合\nを加算\n計 (554, 000 株)\nした株式数から、ツルハHD決算短信に記載された同日現在のツルハH\nDが所有する自己株式 (890, 955 株) を控除した株式数 (49, 220, 113 株) に対す\nるツルハHD株式の割合 (小数点以下第三位を四捨五入。 以下、 所有割合の計算\nにおいて同じとします。) をいいます。\n(注2) 本新株予約権 5, 149 個の内訳は下記のとおりです。\n新株予約権の名称 2025 年2 月 28 日現在の個数 | 目的となるツルハHD株式数\n(個) (株)\n2008 年新株予約権 44 8, 800\n2009 年新株予約権 48 9, 600\n2010 年新株予約権 53 10, 600\n2011 年新株予約権 71 14, 200\n2012 年新株予約権 68 13, 600\n2013 年新株予約権 33 6, 600\n2014 年新株予約権 32 6, 400\n2015 年新株予約権 20 4, 000\n2016 年新株予約権 22 4, 400\n第 11 回新株予約権 4, 758 475, 800\n(i) 本日時点\nウエルシアHD イィオン ツルハHDその他株主\nその他株主 (野村誇券を含む、以下同じです。)\n49.499% 50.51% 9.66% 80.34%\nウエルシアHD ツルバハHD\n(ii) イオンによるツルハHDの持分法適用関連会社化時点\nウエルシアHD ォン ツルハHD\nその他株主 その他株主\n49. 49% 50.51% 26.83% 73.17%\nウエルシアHD ツルハHD\n(各) 本株式交換の効力発生時点 (2025 年 12 月 1 日予定)\nイィイオン ツルハHDその他株主\n(旧ウェルシアHDその他株主を含む)\n39.09% 1 | 60.91%\nツルハHD\nャ 100.00%\nウエルシアHD\n(iv) 本公開皿付け成立時点\nイィオン ツルハHDその他株主\n(旧ウェエルシアHDその他株主を含む)\n50.90% 1 49.1096\nツルハHD\n| 100.00%\nウエルシアHD\n(2) 業務提携の内容\n本資本業務提携最終契約において、イオン、 ツルハHD及びウエルシア日Dが合意\nている業務提携 (以下「本業務提携」といいます。) の内容は以下のとおりです。 本業\n務提携によるシナジーとして 3 か年でおよそ 500 億円を見込んでおります。\ni ) 店舗開発、調剤併設化等に関する相互協力\ni) 商品や電力の仕入れ・開発等の相互協力\n損) 物流効率化の相互協力\niv) 決済・ポイントシステ△・デジタルマーケティング・保険等に関する提携\n) プライベートブランド商品の共同開発相互供給の推進\n) DX・ECの推進等に関する相互協力\n) 経営ノウハウの交流\n)\n)\nフード&ドラックグ業態の研究と推進\n人材及び人事情報の交流\nイオン、 ツルハHD及びウエルシアHDは、イオングループ、 ツルハグループ及びウ\nエルシアグループの経営資源を最大限に活用し、連携することにより、様々な分野でシ\nナジーを発揮して、 日本最大のドラッグストア連合体を創成し、 競争力の獲得、アジア\n5\n川間\n長機会を創\nエルシアグループの中長}\nりました。\n(ア) ドミナント戦\n(注) を推進するこ\n(イ) 海外有\nしてツルハHDが海\nまた、早#\nグループ及びウエルシア グルー\nN市場への展開を一\n(エ)\n達等\n(キ) 調剤朱\nNo. 1のグローバル企業への成長を目指すとともに\n出することを目指すことで、今後のイオングループ、 ツルハグループ及びウ\n可能であると考えるに至\n、具体的には、以\nイオングルーデプ、\nるコスト削減\n開の加速\nイオングループの\nることが\n期的な企業1\ni値の向上を区\nドのようなシナジーを想定しております。\n、そこで働く従業員の限りない成\n許の推進・店舗開発ノウハウの共有による収益性の向上(上記 G))\nツルハグループ及びウエルシアグループは、ドミナント戦略\nとで、 認知度の強化による集客の増カ\nを実現し、 収益性の改善を目指します。\n(注) ドミナント戦略とは、特定の地域に集中して店舗を昌\nける競争優位性を確保する戦略をいいます。\n(上記 G))\n海外ヨ\n外に出店することで、出店スピードの向 上を\nに競争力を獲得するこ RM\nことって重要な経党課題である中国・\n(ウ) 商品等の調達に\nにすることが捉能とをとこち\nおける連携 (上記 ())\n『業拠点や調達網、システ△・ノウハウ、人\nH、 販売促進・\nるこ\nれによ\n的資産を利\n配送の効率\nH店 し、その地域にお\nとができ、\nり、ツルハ\n△SE△\nります。\nイオングループ、ツルハグループ及びウエルシアグループ間で商品等の調達に\nおける連携 (例えば、\n目指します。\n電力の共同調達(\n合同商談や共同配送、\nこよるコスト削減 (上記 ())\n共同販促等) を強化し、 競争力向上を\nイオングループ、 ツルハグループ及びウエルシアグループの間で、 電力の共同調\nこ取り組むこと\nで、コスト低減を目指します。\n(オ) 共同配送による\n配送ル\n共同配送や配送セ\nこはイオングループの物流機能との局\nながると考えております。\n(カ) PB商品の開発加速・\nイオングループ、\n携 (たとえば、 商品の共同企画・開発、\n商品を拡大することで、f\nします。\n局事業に\nおける既存事業強化・新規事業展開\nンターの共同利\n品揃え強化による収益改善 (上記 (v))\nツルハグループ及びウエルシアグループは、 商品開発に係る連\n共同マーケティングなど) を強化し、PB\nお客相\n格・価値訴求力を高め、\n開和人W 配送コストの削減 (上記 (病))\nこより物流効率を最適化し、 また、 将来的\nを培める ことで、配送コストの削減につ\nまの来店頻度の向上を目指\nによる売上増 (上記 (wi) )\nイオングループ、 ツルハグループ及びウエルシアグループ間で、 調剤業務や医院\n経営統合の推進体制及びツルハHDの経営体制\n(1 ) 2025 年4月以降、本局\n結子会社化完了までの推進体制\n6\n誘許のオペベレーションのノウハウの共有・地域～との調剤戦略の最適化を通じ、既\n存事業の売上増加やコスト削減が可能と考えております。\nイオン、 ツルハHD及びウエルシアHDは、 本資本業務提携最終下約に係る資本業務\n提携の目的を実現するため、以下の推進体制を設けます。\n①ステアリングコミッティの設置\n本業務提携の推進、 協業実現に関するヨ\n実績管理、 協議事項その他本資本業務提携に係るヨ\n認める事項の検討、 議論を行うための会合として、\nといいます。) を設置し、本資本業務提携最終契約締結日以降も、本公開買付\n人日又は本資本業務提携最終契約が終\nを目安として継続して開\n協議会」\nけの決済開\n本協議会を3か月に1\n日\n『項について、 意見交換を行い、本業務提携の\n『業の推進のために全当事者が必要と\nステアリングコミッティ (以下「本\n了する日のいずれか早い日までの間、\n八します。 ステアリングコミッティの\n具体的な運営方法、協議事項及び構成員等の詳細については、 別途イオン、ツルハHD\n及びウエノ\nシア量Dの\n上\n定しています。\n②中期経営\nといいます。) の\nとする数値月標の設定及び各ヨ\nする中期経営計画策定委員会を設置します。中期経営ョ\nイチェーン、IT システ△、決済・ポイント、\nに分科会を設置し、シナジーの創H\nシナジー創\nープにおける商品\n株式交換後、TGMDの取締役は、ツルハHDとウェ\nするとともに、両社より～任された取締役からそれぞれ1名を代表取締役とする予\n定です。\nなお、イオン、ツルハHD及びウエルシアHDは、TGMDによるシナジー創出\n及び規模を別途協議のうえ、中\n下に設置するサプライチェーン分科会と財\nについて、\n計画策定委員会\n本資本業務提携完了後の統合会社であるツ/\n期経営計画に関わる方針策定、2027\n業分野における目標設定に関する協議、検討を目的と\n前で誠実に協議 し、 合意により決定\nティは、 イオン、 ツルハHD及びウエルシア HD の社長を\n実現時電\nHHにおける商品・物流関係機能の中核子会視\nツルハHD の子会社である株式会社ツルハグループマーチャンダ\n「TGMD」といいます。) を、本資本業務提携による商品・4\nおける中核と位置づけ、ウエルシアグループからTGMDに対\n・物流等の機能及び人員の全部又は一部を移管します。また、本\nシアHDから複数名を～任\n④統合会社 (ツルハHD) の経営体制\n本経営統合を含む本資本業務提携の実施後も、ツルハHDの取締役は、引き続き上\nの当 該会視\n場会社としての自立司\n長が独立社外取締役であるツルハ\nツルハHDが役員～\n員することが明らかであると客観\nハHD\n有\nE 2 月\n調剤、店舗開発、\nHに向けて実務的な検討を行います。\nします。ステアリングコミッ\nP心として構成することを想\n下「統合会社 (ツルハHD)」\n期からの3か年を基本\n[画策定委員会の下に、サプラ\n海外戦略等のテーマ別\n上の活\nジング (以下\n物流のシナジー創出に\nウエルシアグノ\nレ、\nま携して検討します。\n上に係る会社\n[提案を尊重し、当該役員の～人\nを行います\nなお、本株式交換後、\no\nウエルシアHDの役職員から 2名が、統合会社 (ツルバハ\n経営計画策定委員会及びその\nE・独立性に基づき、独立社外取締役が過半数を占め、かつ、議\nHDが設置する指名報酬委員会の答申を踏まえて、\n提案を行い、イオンは、ツルハHD の企業人1\n的かつ合理的に判断される場合を除き、ツルハHH\nEに係る株主総会において匠成の議決権行使\ni値を明\nD\nD) の取締役に就任することが予定されております。 当該取締役を含む本株式交換\n後のツルハHDの取締役の～任に係る議案は、ツルハHDにおいて 2025年5月 26\n日に開催予定の定時株主総会\nが確定しましたら開示いたし3\n7\nにおいて付議することを予定しており、取締役候補者\nます。 詳細については、ツルハHD及びウエルシアH\nDが本日付で公表した「株式会社ツウルハホールディングスとウエルシアホールディ\nングス株式会社の経営統合に関する株式交換契約の締結に関するお知らせ」を～参\n照ください。\n(2) 連結\n本連結子会社化以降もち、ツルハHDは上場を維持しますので、引き続き上場会社\nとしての自立性・独立性に基づき、指名報酬委員会の答申を踏まえて取締役を～任\n結子会社化完了以降の経営体制\nします。なお、ツルハHD は、連結子会社化後の定時株主総会において、イオンが\n指名する非業務執行取締役 1 名の～任議案を、指名報酬委員会の答申を経たうえ\nで、付蔵します。\nなお、2025 年 12 月以降の経営体制については、 2 兆円を超える規模の売上高を有\nする日本最大のドラッグストア連合体として、また、アジアNo. 1 のグローバル企\n業への成長を目指す企業として、最適な経営体制を構築していきます。\nTV. 本資本業務提携の当事会社の概要\n(1) イオン\n① 名 称 | イオン株式会社\n② 所 在 地 | 千葉県千葉市美浜区中瀬一丁目 5番地1\n9 ノ |取締役代表執行役社長 吉田 明夫\n④ 小売、ディベロッパー、金融、サービス及びそれに関連する事\n事 業 内 容| 業を営む会社の株式又は持分を保有することによる当該会社の\n事業活動の管理\n⑤ 資 本 金 | 220, 007 百万円 (2025 年 2 月 28 日現在)\n⑥ 設立年月 日|1926年9月21日\n⑳ 日本マスタートラスト信託銀行株式会社 (信託口) 13.239%\n株式会社日本カストディ銀行(信託口) 4.46%\n株式会社みずほ銀行 3.889%\n還還 公益財団法人間田文化財団 2.57%\n0 内 公益財団法人イオン環境財団 2.5496\n(2024 年8月 31 農林中央金庫 2.12%\n日現在) ST△TE STREET B△NK WEST CLIENT-TRE△TY 505234 1.489%6\n(常任代理人 株式会社みずほ銀行決済営業部)\nオン社員持株会 1.39%\nオン共栄会 (野村誇券口) 1.36%\n東京海上日動火災保険株式会社 1.17%\nに\n当事会社間の関係\n資 本 関係\nオンは、 ツルハHD の普通株式 9, 675, 200 株 (ツルハHDの発\n行株式総数の約 19.54%) を所有しております。\nオンはウエルシア HD の普通株式 105, 981, 400 株(ウエルシア\nHDの発行済株式総数の 50.549%) を所有しております。\n人 的 関 係\nツルハHD及びウエルシアHDに関し、該当事項はありません。\n取 引 関係\nツルハHDとの間で、 業務提携下約を締結しており、 またイオン\nグループとの金融サービスの取引等があります。ウエルシア HD\nとの間で、イオングループとのロイヤルティの支払、消費寄託、\n8\n金融サービスの取引等があります。\nイオンは、 ツルハHD の主要株主である筆頭株主であり、 ツルハ\nHDの関連当事者に該当します。イオンはウエルシアHDの親会\n和 当 状半生に該します。\n⑨ 最近3年間の連結経営成績及び連結財政状態\n決 算 期 2023 年 2 月期 2024 年 2 月期 2025 年 2 月期\n純 次 産 1, 970, 232 百万 2, 087, 201 百万 2, 121, 226 百万F\n総 次 産| 12,341,523 百万円 | 12, 940, 869 百万円 | 13, 833, 319 百万\n1 株当たり純資産額 1,161.12 1, 231.59 1,218.63H\n営業 益| 9,116,823 百万F 9, 553, 557 百万 10, 134, 877 百万\n営業 利益 209, 783 百万 250, 822 百万 237, 747 百万\n経常利益 203, 665 百万 237, 479 百万 224, 223 百万\n親会社の所有者に帰 21, 381 百万 44, 692 百万F 28, 783 百万F\n属 す る\n当 期 純 利 人益\n1 株当たり当期純利益 25.11F 52.25H 33.58\n1株当たり配当額 36F 36F 40F\n(2) ツルハ△HD\n① 名 称 | 株式会社ツルハホールディングス\n② 所 在 地 | 札幌市東区北 24 条東 20丁目1番21号\n者の取科役社長 鈴羽 順\n氏 名\n④ 事 業 内 容| グループ会社の各種事業戦略の実行支援及び経営管理\n⑤ 資 本 金 | 11,626 百万円 (2025 年 2 月 28 日現在)\n⑥ 設立年月 日11963年6月1日\n②⑦ イオン株式会社 19.87%\n日本マスタートラスト信託銀行株式会社 (信託口) 15.23%\n野村誇券株式会社 6.79%\nCEP LUX-ORBIS SIC△V 4.47%\n(常任代理人 シティバンク、エヌ・エイ東京支店\nカストディ業務部長)\n大株主及び持株 株式会社日本カストディ銀行 (信託口) 3.75%\n比 率 ST△TE STREET B△NK △ND TRUST CLIENT OMNIBUS 3.00%\n(2024 年 11 月 △CCODN 0M02 505002 ーー\n15 日現在) NM 代理人 株式会社みずほ銀行 決済営業部部\n鈴羽 樹 2.90%\n稚羽 弘子 2.81%\nST△TE STREET B△NK △ND TRUST COMP△NY 505001 2.249%6\n(常任代理人 株式会社みずほ銀行 決済営業部部\n長)\n稚羽 暁子 2.149%\n当事会社間の関係\nイオンは、 ツルハHD の普通株式 9, 675, 200 株 (ツルハHDの発\n行済株式総数の約 19. 549%) を所有しております。\nウエルシアHDは、ウエルシア HD の子会社であやるウエルシア薬\n局株式会社を通じして、 ツルハHDの普通株式 4. 000 株 (ツルハH\nD の発行済株式総数の約 0.01%) を所有しております。\n人 的 関 係] 該当事項はありません。\nイオンとの間で、 業務提携下約を締結しており、 また、イオング\n取 引 関 係]ループとの金融サー ビスの取引等があり ます。\nウエルシアHDとの間で、該当事項はありません。\nイオンは、 ツルハHD の主要株主である筆頭株主でもり、 ツルハ\n関連当事者への| HDの関連当事者に該当します。\n該当 状 況|ウエルシアHDは、イオンの子会社であやることから、 ツルハHD\nの関連当事者に該当します。\n⑨ 最近3年間の連結経営成績及び連結財政状態\n決 算 其 2023 年 5月期 2024 年 5 月期 2025 年 2 月期\n純 次 産 304, 144 百万 305, 297 百万 306, 377 百万\n総 次 産 539, 830 百万 549, 551 百万 583, 362 百万\n1 株当たり純資産額 5, 690.49F 5, 748.63F 5, 778.90P\n売 上 高 970, 079 百万 1, 027, 462 百万 845, 603 百万\n営業 利益 45, 572 百万F 47, 151 百万P 37, 894 百万F\n経常利益 45, 689 百万 47, 466 百万F 37, 840 百万F\n親会社の所有者に帰 25, 258 百万円 21, 743 百万円 17, 207 百万円\n属 す る\n当 期 純 利 益\n1 株当たり当期純利益 519.90H 447.27F 353.67F\n1株当たり配当額 260F 267F 267F\n(注) ツルハHD は、2025 年 2 月期より決算期 (事業年度の末日) を5月 15 日から2月末\n日へ変更しております。この変更に伴い、2025 年 2 月期は決算期変更の経過期間となるこ\nとから、2024 年5月 16 日から 2025 年2月 28 日までの9.5 ヶ月間の変決算となっており\nます。\n(3) ウエルシアHD\n① 名 称 | ウエルシアホールディングス株式会社\n② 所 在 地 | 東京都千代田区外神田二丁目2番15号\n9 NM ノ | 代表取科藤和貞最高業務才和作者 柚 蘭\n④ 事 業 内 容 調剤併設型ドラッグストアチェーンの運営を行う子会社及びグ\nループ会社の経営管理等\n⑤ 資 本 金 | 7, 792 百万円 (2025 年 2 月 28 日現在)\n⑥ 設立年月 日12008年9月1日\n②⑦ イオン株式会社 50.54%\n日本マスタートラスト信託銀行株式会社 ( 5.20%\n大株主及び持株| ーー\n比 率 | ノエルシアホールディングス従業員持株会 2.11%\n(2025 年 2月 28 | 株式会社日本カストディ銀行 (信託口) 1.69%\n日現在 株式会社ツルハ 1.60%\nSMBC日興証券株式会社 1.22%\n野村信託銀行株式会社 (投信口) 0.98%\n10\n株式会社日本カストディ銀行 (信託E口) 0.81%\nCEP LUX-ーORBIS SIC△V 0.79%\n株式会社イシダ 0.77%\n⑧ 当事会社間の関係\nイオンは、ウエルシア HD の普通株式 105, 981, 400 株 (ウエル\nシアHD の発行済株式総数の約 50.54%) を所有しております。\n次 本 関 係| ツルハHDは、ツルハHD の子会社である株式会社ツルハを通\nじて、ウエルシア了HDの普通株式 3, 352, 592 株 (ウエルシア是\nDの発行済株式総数の約 1.60%) を所有しております。\nンに関し、イオン取締役兼代表執行役会長岡田元也氏が取\n人 的 関 係| 締役に就任しております。 ツルハHDに関し、該当事項はありま\nの\nンに関ししイオングループとのロイヤルティの支払、 消費寄\n取 引 関係|託、 WiNG スの取引等があります。 ツルハHDに関し、 該当\n事項はありません。\n関連当事者への オンは、 ウエルシア HDの親会社に該当します。 親会社である\nュー レー am オンは、ツルハHD の主要株主である筆頭株主であり、ツルハ\n族 当 状 潮| 語の関連当事者に該当します。\n⑨ 最近3年間の連結経営成績及び連結財政状態\n決 算 期| 2023年2月期 2024 年 2 月期 2025 年 2 月期\n純 次 産 232, 384 百万 244, 367 百万 254, 486 百万\n総 次 産 537, 362 百万 551, 860 百万上 579, 985 百万\n1 株当たり純資産額 1,078.97 1, 149.88 1,197.11H\n売 上 高| 1.144, 278 百万円 | 1, 217, 339 百万F 1, 285, 005 百万\n営業 利益 45, 635 百万P 43, 231 百万P 36, 409 百万P\n経常 利益 52, 149 百万F 47, 756 百万P 40, 837 百万\n親会社の所有者に帰属 27, 030 百万F 26, 451 百万 14, 958 百万\nす る\n当 期 純 利 益\n1 株当たり当期純利益 129.38F 127.83F 72.23H\n1株当たり配当額 32.00H 34.00H 36.00H\nYV. 資本業務提携の日程\n2024 年 2 月 28 日付資本業務提携胡約の締結日 2024 年2月 28 日\n本資本業務提携最終契約締結の代表執行役決定日 | 本日\n(イオン)\n本資本業務提携最終契約及び本株式交換契約締結\nの取締役会決議日 (ツルハHD・ウエルシアH\nD)\n本資本業務提携最終契約及び本株式交換契約の締 | 本日\n結晶\nイオンによるツルハHD株式の追加取得\n2025 年5月頃 (予定)\n本株式交換契約の承認に係るツルハHD株主総会\n～でで\n2025年5月26日 (予定)\n本株式交換契約の承認に\n総会\n係るウエルシアHD株ヨ\n[\n2025年5月27日 (予定)\n11\nウエルシアHDの上場廃止\n2025 年 11月27 日 (予定)\n本株式交換の効力発生\n2025年12月1日 (予定)\n本公開皿付けの開始\n2025 年 12 月上旬 (予定)\nWI. その他\n本資本業務提携最終契約がイオン、ツルハHD及びウエルシアHD の当期の業績に与え\n影響は軽微ですが、』\n洲\n必要性が4\n以降 の業績に\nW. 支配株ヨ\nEじた場合、\n事項が生じた場合には、速やか!(\nこ与え\n速やか(\n長期的に には各社の業績の向上\n影響については\nに開示いたします。\nEとの取引等に関する事項\n(1)\nしている「\nは、「支配株主と\n規に従い、\n配株主との取引等の\nウエルシアHDに』J\n会社であり支\nに該当します。\nウエルシアHH\n配株主\nDが 2024和\n該 の\n性及び少数株主の保護の方策に関する指針への適合\nトる本資本業務提携最終契約の締結は、イオンがウエノ\nに当たることから、ウエルシアHDにとって支配株主との\n配株主との\nにあたっては一般的な取\nついて確認のうえ決定を行い、\n必要に応じて\n取\n8\n引箸\nの取引については、会社法等の関係法\n締役会の承認\n条件と同等\nを行う際に\nるテクし\n上に資するものと考えております。 なお、\n、 現在精査中であり、 今後影響等が】\nこ開示いたします。その他に関しましてもゃ、 今後、\n前明し、 開示の\n公表すべき\n状況\nDの\n引等\nシア\nE6 月 28 日に開示したコーポレート・ガバナンス報告書で示\nおける少数株主の保護の方策に\nこ関する指針」\n令及び取締役\n得るものとしております。\nであるかなど取引\n少数株主(\nこ不利益を与えることがないよ う5\n応していく方針であります。」と記載しております。\nこの点、ウエルシアHDは、本資本業務提携最\n(3) 了骸のとおり、その公正性を担保\nに記\n終契約の締結に\nし、利益相反を回避するた\n会規程\n内容の受当 性や経済合\n等の社内\n役会の承認\n理性に\n、 適切に対\n取締\nうに\n際して、下記 (2) 及\nめの措置を講じ\nており、 本資本業務提携最終契約の締結は上記のウエルシアHDの「支配株主との取引\n等を行う際に\nます。\n(2) 公正\nして、\n①\n性を担保するため\nイオン、ツ/\nエルシアHD社外』\n査役・双護士) 及\nおける少数株主の保護の方策に\nの\nレ\n弟置及び利益相反を\nウエルシアHDは、本資本業務提携最終契約の締結の公正\n以下の各措置を実施\nハHD及びウエルシアHDから独立した委員3名 (ー\n関する指針」 に適合してい\nロ\n避するための措置に\n性を担保す\nております。\nび\n彦氏 (ベネディ\n公認会計士)) (\n関\nると考えており\nする事項\nるための措置と\n沢勝氏 (ウ\n締役・独立役員)、加々美博久氏 (ウエルシア耳D元社外監\n・コンサルティング代表取締役社長\nこより構成する特別委員会 (以下「本特別委員会 (ウエルシア是\n地\n\\います。) 1\nD)」といいます。) を設置 した上で 同委員会から、 了M△N\n締結及び同契約に基づく本経営統合 (以下「本経営統合等」とv\nエルシアHDの企業価値の向上に <和するものであり、 本経営統合\nさとナー\nとは合理的であると考えられること、本株式交換に係る割当比率を含め本経営統\n合等の取引条件は受当であると考えられること、 及び、 本経営統合\nエルシアHD 取締役\n契約の締結に\n会が本経\n等の手続は公\n正であると考えられることから、本特別委員会 (ウエルシアHD) は、⑬ウエル\nシア HD取締役会に対 し、 本経営統合等の実施することを勧告するとともに\n、ウ\n統合等の実施に関する決定 (本資\n係る決定を含む。) を行うこ\nことは、ウエルシアHD\n12\n本業務提携最終\nの少数株主にと\n各措置の詳細につきましては、ツルハHD及びウエルシアHDが本日人\nって不利益なものでないものと思料する旨を内容とする箸月\n(ウエルシア HD)」といいます。) を取得\nイオン、ツルハHD及びウエルシアHDから独立した財務アドバイサ\n者算定機関であわるみずは証券株式会社から、株式交換比率算定\n当比率がウエルシアHDの普通株\nに係る害\n左\n計\nると判断\nイオン、\n森・縮\nウエノ\n務提携最終契約\nウエノ\nを兼任する岡田元也氏) を除く出\nい監査役全員による異議がない旨の意見\nする旨の意見\n用当\n松本法有\nほ務所外\n玉|\n法共同\n記\n表\n(以 B\n「本侍昌\n圭:\n青\nが一及び第三\n及び本株式交換\n書\n三!\nEにとって財務的見地から妥当であ\n(フェアネス・オピニオン) を取得\nツルハHD及びウエルシア HDから独立 した法務アドバイザーである\n『業から、法的観点の助言を取得\nシアHDにおける、 イオン及びツルハHDから独立した立場で、 本資本業\n及び本経営統合に係る検討、交渉及び判断を行う体制の構築\nシアHDにおける利害関係を有する取締役(イオンの取締役半\n代表執行役\n席取締役全員による承認及び利害関係を有しな\n「で公表 した\n「株式会社ツルハホールディングスとウエルシアホールディングス株式会社の経営統\n合に関する株式交換契約の締結に関するお知らせ」の「3. 本株式交換に係る割当ての\n内容の根拠等」の「(4) 公」\n置を含む。)」を～参照ください。\n(3) 当該取引等が少数株ヨ\n係のない者から入ヨ\nウエルシアHDは、2025 有\n上記「\nJlml |\nほ項」の①に記載のとおり、ウエルシアH\nことを勧告するとともに、ウエルシア H\nFした意見の概要\nE4月 11 日信\nE性を担介するための措置及び利益和\n(2) 公]\nD\n旧反を\n日\nE性を担保するための措置 (利益相反を\nEにとって不利益なものでないことに関する、支配株\n日\n避するための措\nと利害関\n「で、本特別委員会 (ウエルシアHD) から、\n避するための措置に関する\nD取締役会に対し、 本経営統合等の実施する\n取締役会が本経営統合等の実施に関する決定\n(本資本業務提携最終契約の締結に係る決定を含む。) を行うことは、ウエルシアHD\nの少数株主にとって不利益なちのでないものと思料する旨を内容とする本徐明\nルシアHHD) を受領しております。 本答\nB書\nB書\n(ウェ\n(ウエルシア是D) の詳細につきましては、\nツルハ是D及びウエルシア是Dが本日付で公表 した 「株式会社ツウルハホールディングス\nとウエルシアホールディングス株式会社の経営統合に関する株式交換契約の締結に関\nするお知らせ」の「3. 本株式交\n保するための指置 (利益相反を\nおける利害関係を有しない特別委員会からの稚朋\n日\n換に係る割当ての内容の根拠等」 の「(4) 公1\n避するための措置を含む。)」の「①ウエルシアHDに\nB書の取得」を～参照ください。\nE性を担\n(参考)\n(1) イオン\n(単位 : 百万円)\n親会社株主に帰\n営業収益 営業利益 経常利益 属する当期純利\n益\n当期連結業績予想\n10, 500, 000 270, 000 250, 000 40, 000\n(2026 年 2 月期)\n前期連結実績\n10, 134, 877 237, 747 224, 22328, 783\n(2025 年 2 月期)\n13\n(2) ツルハHD\n(単位 : 百万円)\n親会社株主に帰\n売上高 営業利益 経常利益 属する当期純利\n益\n当期連結業績予想\n(2026 年2月期 1, 113, 400 51, 100 50, 300 24, 800\n前期連結実績 845, 603 37, 894 37, 840 17, 207\n(2025 年 2月期 - ーー ・\n(3) ウエルシアHD\n(単位 : 百万円)\n親会社株主に帰\n売上高 営業利益 経常利益 属する当期純利\n益\n当期連結業績予想\n(2026 年 2 月期) 685, 100 20, 500 22, 700 12, 500\n第 2 四半\n前期連\n(2025 年2月期 1, 285, 005 36, 409 40, 837 14, 958\n(注) ウエルシアHDは、ツルハHDとの経営統合を予定しており、2025 年 11 月 27 日を\nもって上場廃止になる予定でやるため、通期連結業績予想の公表を控えさせていただきま\nす。\n14\n以 上",
    "tables": [
      "2023年2月期 2024 年 2 月期 2025 年 2 月期\n純 次 産 232, 384 百万 244, 367 百万 254, 486 百万\n総 次 産 537, 362 百万 551, 860 百万上 579, 985 百万\n1 株当たり純資産額 1,078.97 1, 149.88 1,197.11H\n売 上 高| 1.144, 278 百万円 | 1, 217, 339 百万F 1, 285, 005 百万\n営業 利益 45, 635 百万P 43, 231 百万P 36, 409 百万P\n経常 利益 52, 149 百万F 47, 756 百万P 40, 837 百万\n親会社の所有者に帰属 27, 030 百万F 26, 451 百万 14, 958 百万\nす る\n当 期 純 利 益\n1 株当たり当期純利益 129.38F 127.83F 72.23H\n1株当たり配当額 32.00H 34.00H 36.00H\nYV. 資本業務提携の日程\n2024 年 2 月 28 日付資本業務提携胡約の締結日 2024 年2月 28 日\n本資本業務提携最終契約締結の代表執行役決定日 | 本日\n(イオン)\n本資本業務提携最終契約及び本株式交換契約締結\nの取締役会決議日 (ツルハHD・ウエルシアH\nD)\n本資本業務提携最終契約及び本株式交換契約の締 | 本日\n結晶\nイオンによるツルハHD株式の追加取得\n2025 年5月頃 (予定)\n本株式交換契約の承認に係るツルハHD株主総会\n～でで\n2025年5月26日 (予定)\n本株式交換契約の承認に\n総会\n係るウエルシアHD株ヨ\n[\n2025年5月27日 (予定)\n11\nウエルシアHDの上場廃止\n2025 年 11月27 日 (予定)\n本株式交換の効力発生\n2025年12月1日 (予定)\n本公開皿付けの開始\n2025 年 12 月上旬 (予定)\nWI. その他\n本資本業務提携最終契約がイオン、ツルハHD及びウエルシアHD の当期の業績に与え\n影響は軽微ですが、』\n洲\n必要性が4\n以降 の業績に\nW. 支配株ヨ\nEじた場合、\n事項が生じた場合には、速やか!(\nこ与え\n速やか(\n長期的に には各社の業績の向上\n影響については\nに開示いたします。\nEとの取引等に関する事項\n(1)\nしている「\nは、「支配株主と\n規に従い、\n配株主との取引等の\nウエルシアHDに』J\n会社であり支\nに該当します。\nウエルシアHH\n配株主\nDが 2024和\n該 の\n性及び少数株主の保護の方策に関する指針への適合\nトる本資本業務提携最終契約の締結は、イオンがウエノ\nに当たることから、ウエルシアHDにとって支配株主との\n配株主との\nにあたっては一般的な取\nついて確認のうえ決定を行い、\n必要に応じて\n取\n8\n引箸\nの取引については、会社法等の関係法\n締役会の承認\n条件と同等\nを行う際に\nるテクし\n上に資するものと考えております。 なお、\n、 現在精査中であり、 今後影響等が】\nこ開示いたします。その他に関しましてもゃ、 今後、\n前明し、 開示の\n公表すべき\n状況\nDの\n引等\nシア\nE6 月 28 日に開示したコーポレート・ガバナンス報告書で示\nおける少数株主の保護の方策に\nこ関する指針」\n令及び取締役\n得るものとしております。\nであるかなど取引\n少数株主(\nこ不利益を与えることがないよ う5\n応していく方針であります。」と記載しております。\nこの点、ウエルシアHDは、本資本業務提携最\n(3) 了骸のとおり、その公正性を担保\nに記\n終契約の締結に\nし、利益相反を回避するた\n会規程\n内容の受当 性や経済合\n等の社内\n役会の承認\n理性に\n、 適切に対\n取締\nうに\n際して、下記 (2) 及\nめの措置を講じ\nており、 本資本業務提携最終契約の締結は上記のウエルシアHDの「支配株主との取引\n等を行う際に\nます。\n(2) 公正\nして、\n①\n性を担保するため\nイオン、ツ/\nエルシアHD社外』\n査役・双護士) 及\nおける少数株主の保護の方策に\nの\nレ\n弟置及び利益相反を\nウエルシアHDは、本資本業務提携最終契約の締結の公正\n以下の各措置を実施\nハHD及びウエルシアHDから独立した委員3名 (ー\n関する指針」 に適合してい\nロ\n避するための措置に\n性を担保す\nております。\nび\n彦氏 (ベネディ\n公認会計士)) (\n関\nると考えており\nする事項\nるための措置と\n沢勝氏 (ウ\n締役・独立役員)、加々美博久氏 (ウエルシア耳D元社外監\n・コンサルティング代表取締役社長\nこより構成する特別委員会 (以下「本特別委員会 (ウエルシア是\n地\n\\います。) 1\nD)」といいます。) を設置 した上で 同委員会から、 了M△N\n締結及び同契約に基づく本経営統合 (以下「本経営統合等」とv\nエルシアHDの企業価値の向上に <和するものであり、 本経営統合\nさとナー\nとは合理的であると考えられること、本株式交換に係る割当比率を含め本経営統\n合等の取引条件は受当であると考えられること、 及び、 本経営統合\nエルシアHD 取締役\n契約の締結に\n会が本経\n等の手続は公\n正であると考えられることから、本特別委員会 (ウエルシアHD) は、⑬ウエル\nシア HD取締役会に対 し、 本経営統合等の実施することを勧告するとともに\n、ウ\n統合等の実施に関する決定 (本資\n係る決定を含む。) を行うこ\nことは、ウエルシアHD\n12\n本業務提携最終\nの少数株主にと\n各措置の詳細につきましては、ツルハHD及びウエルシアHDが本日人\nって不利益なものでないものと思料する旨を内容とする箸月\n(ウエルシア HD)」といいます。) を取得\nイオン、ツルハHD及びウエルシアHDから独立した財務アドバイサ\n者算定機関であわるみずは証券株式会社から、株式交換比率算定\n当比率がウエルシアHDの普通株\nに係る害\n左\n計\nると判断\nイオン、\n森・縮\nウエノ\n務提携最終契約\nウエノ\nを兼任する岡田元也氏) を除く出\nい監査役全員による異議がない旨の意見\nする旨の意見\n用当\n松本法有\nほ務所外\n玉|\n法共同\n記\n表\n(以 B\n「本侍昌\n圭:\n青\nが一及び第三\n及び本株式交換\n書\n三!\nEにとって財務的見地から妥当であ\n(フェアネス・オピニオン) を取得\nツルハHD及びウエルシア HDから独立 した法務アドバイザーである\n『業から、法的観点の助言を取得\nシアHDにおける、 イオン及びツルハHDから独立した立場で、 本資本業\n及び本経営統合に係る検討、交渉及び判断を行う体制の構築\nシアHDにおける利害関係を有する取締役(イオンの取締役半\n代表執行役\n席取締役全員による承認及び利害関係を有しな\n「で公表 した\n「株式会社ツルハホールディングスとウエルシアホールディングス株式会社の経営統\n合に関する株式交換契約の締結に関するお知らせ」の「3. 本株式交換に係る割当ての\n内容の根拠等」の「(4) 公」\n置を含む。)」を～参照ください。\n(3) 当該取引等が少数株ヨ\n係のない者から入ヨ\nウエルシアHDは、2025 有\n上記「\nJlml |\nほ項」の①に記載のとおり、ウエルシアH\nことを勧告するとともに、ウエルシア H\nFした意見の概要\nE4月 11 日信\nE性を担介するための措置及び利益和\n(2) 公]\nD\n旧反を\n日\nE性を担保するための措置 (利益相反を\nEにとって不利益なものでないことに関する、支配株\n日\n避するための措\nと利害関\n「で、本特別委員会 (ウエルシアHD) から、\n避するための措置に関する\nD取締役会に対し、 本経営統合等の実施する\n取締役会が本経営統合等の実施に関する決定\n(本資本業務提携最終契約の締結に係る決定を含む。) を行うことは、ウエルシアHD\nの少数株主にとって不利益なちのでないものと思料する旨を内容とする本徐明\nルシアHHD) を受領しております。 本答\nB書\nB書\n(ウェ\n(ウエルシア是D) の詳細につきましては、\nツルハ是D及びウエルシア是Dが本日付で公表 した 「株式会社ツウルハホールディングス\nとウエルシアホールディングス株式会社の経営統合に関する株式交換契約の締結に関\nするお知らせ」の「3. 本株式交\n保するための指置 (利益相反を\nおける利害関係を有しない特別委員会からの稚朋\n日\n換に係る割当ての内容の根拠等」 の「(4) 公1\n避するための措置を含む。)」の「①ウエルシアHDに\nB書の取得」を～参照ください。\nE性を担\n(参考)\n(1) イオン\n(単位 : 百万円)\n親会社株主に帰\n営業収益 営業利益 経常利益 属する当期純利\n益\n当期連結業績予想\n10, 500, 000 270, 000 250, 000 40, 000\n(2026 年 2 月期)\n前期連結実績\n10, 134, 877 237, 747 224, 22328, 783\n(2025 年 2 月期)\n13\n(2) ツルハHD\n(単位 : 百万円)\n親会社株主に帰\n売上高 営業利益 経常利益 属する当期純利\n益\n当期連結業績予想\n(2026 年2月期 1, 113, 400 51, 100 50, 300 24, 800\n前期連結実績 845, 603 37, 894 37, 840 17, 207\n(2025 年 2月期 - ーー ・\n(3) ウエルシアHD\n(単位 : 百万円)\n親会社株主に帰\n売上高 営業利益 経常利益 属する当期純利\n益\n当期連結業績予想\n(2026 年 2 月期) 685, 100 20, 500 22, 700 12, 500\n第 2 四半\n前期連\n(2025 年2月期 1, 285, 005 36, 409 40, 837 14, 958\n(注) ウエルシアHDは、ツルハHDとの経営統合を予定しており、2025 年 11 月 27 日を\nもって上場廃止になる予定でやるため、通期連結業績予想の公表を控えさせていただきま\nす。\n14\n以 上"
    ]
  }
]